Workbook

Sheet suppliers_coldchain
A1: supplier_id | B1: supplier_name | C1: supplier_type | D1: country | E1: lead_time_days | F1: payment_terms_days | G1: service_level | H1: active_flag | I1: risk_score | J1: primary_contact
A2: SUP00001 | B2: Supplier 001 | C2: Importer | D2: UK | E2: 14 | F2: 15 | G2: B | H2: N | I2: 80 | J2: contact001@example.com
A3: SUP00002 | B3: Supplier 002 | C3: Local Partner | D3: UK | E3: 7 | F3: 45 | G3: A | H3: N | I3: 40 | J3: contact002@example.com
A4: SUP00003 | B4: Supplier 003 | C4: Primary Manufacturer | D4: UAE | E4: 9 | F4: 60 | G4: C | H4: N | I4: 61 | J4: contact003@example.com
A5: SUP00004 | B5: Supplier 004 | C5: Importer | D5: South Africa | E5: 19 | F5: 60 | G5: A | H5: Y | I5: 64 | J5: contact004@example.com
A6: SUP00005 | B6: Supplier 005 | C6: Local Partner | D6: Morocco | E6: 6 | F6: 30 | G6: B | H6: N | I6: 63 | J6: contact005@example.com
A7: SUP00006 | B7: Supplier 006 | C7: Importer | D7: Egypt | E7: 6 | F7: 45 | G7: B | H7: Y | I7: 68 | J7: contact006@example.com
A8: SUP00007 | B8: Supplier 007 | C8: Distributor | D8: South Africa | E8: 13 | F8: 60 | G8: C | H8: Y | I8: 46 | J8: contact007@example.com
A9: SUP00008 | B9: Supplier 008 | C9: Distributor | D9: Ghana | E9: 11 | F9: 45 | G9: A | H9: Y | I9: 64 | J9: contact008@example.com
A10: SUP00009 | B10: Supplier 009 | C10: Distributor | D10: South Africa | E10: 10 | F10: 30 | G10: A | H10: Y | I10: 34 | J10: contact009@example.com
A11: SUP00010 | B11: Supplier 010 | C11: Primary Manufacturer | D11: Nigeria | E11: 8 | F11: 15 | G11: A | H11: Y | I11: 84 | J11: contact010@example.com
A12: SUP00011 | B12: Supplier 011 | C12: Primary Manufacturer | D12: UAE | E12: 17 | F12: 60 | G12: C | H12: N | I12: 69 | J12: contact011@example.com
A13: SUP00012 | B13: Supplier 012 | C13: Local Partner | D13: Nigeria | E13: 3 | F13: 60 | G13: B | H13: Y | I13: 55 | J13: contact012@example.com
... A121: SUP00120 | B121: Supplier 120 | C121: Primary Manufacturer | D121: Nigeria | E121: 4 | F121: 45 | G121: A | H121: Y | I121: 66 | J121: contact120@example.com

Sheet products_coldchain
A1: product_id | B1: sku | C1: product_name | D1: category | E1: uom | F1: primary_supplier_id | G1: storage_temp_min_c | H1: storage_temp_max_c | I1: shelf_life_days | J1: standard_cost | K1: standard_price | L1: fefo_required | M1: active_flag
A2: PRD00001 | B2: CC-0001 | C2: Baby Food Item 001 | D2: Baby Food | E2: Jar | F2: SUP00034 | G2: 4 | H2: 8 | I2: 45 | J2: 13.36 | K2: 20.72 | L2: N | M2: Y
A3: PRD00002 | B3: CC-0002 | C3: Premium Cheese Item 002 | D3: Premium Cheese | E3: Kg | F3: SUP00012 | G3: 2 | H3: 8 | I3: 120 | J3: 5.85 | K3: 14.27 | L3: Y | M3: Y
A4: PRD00003 | B4: CC-0003 | C4: Herbs Item 003 | D4: Herbs | E4: Bundle | F4: SUP00015 | G4: 1 | H4: 6 | I4: 45 | J4: 15.41 | K4: 31.16 | L4: Y | M4: Y
A5: PRD00004 | B5: CC-0004 | C5: Ready Meal Item 004 | D5: Ready Meal | E5: Tray | F5: SUP00036 | G5: 0 | H5: 5 | I5: 60 | J5: 4.96 | K5: 7.2 | L5: N | M5: Y
A6: PRD00005 | B6: CC-0005 | C6: Seafood Item 005 | D6: Seafood | E6: Kg | F6: SUP00088 | G6: -2 | H6: 4 | I6: 90 | J6: 2.05 | K6: 2.79 | L6: N | M6: Y
A7: PRD00006 | B7: CC-0006 | C7: Ready Meal Item 006 | D7: Ready Meal | E7: Tray | F7: SUP00090 | G7: 0 | H7: 5 | I7: 30 | J7: 8.14 | K7: 10.99 | L7: N | M7: Y
A8: PRD00007 | B8: CC-0007 | C8: Herbs Item 007 | D8: Herbs | E8: Bundle | F8: SUP00084 | G8: 1 | H8: 6 | I8: 45 | J8: 12.87 | K8: 25.48 | L8: Y | M8: Y
A9: PRD00008 | B9: CC-0008 | C9: Fresh Dairy Item 008 | D9: Fresh Dairy | E9: Kg | F9: SUP00003 | G9: 2 | H9: 6 | I9: 14 | J9: 15.41 | K9: 21.55 | L9: Y | M9: Y
A10: PRD00009 | B10: CC-0009 | C10: Seafood Item 009 | D10: Seafood | E10: Kg | F10: SUP00023 | G10: -2 | H10: 4 | I10: 10 | J10: 3.74 | K10: 8.63 | L10: Y | M10: Y
A11: PRD00010 | B11: CC-0010 | C11: Ready Meal Item 010 | D11: Ready Meal | E11: Tray | F11: SUP00096 | G11: 0 | H11: 5 | I11: 60 | J11: 4.91 | K11: 6.85 | L11: Y | M11: Y
A12: PRD00011 | B12: CC-0011 | C12: Chilled Juice Item 011 | D12: Chilled Juice | E12: Litre | F12: SUP00082 | G12: 2 | H12: 8 | I12: 7 | J12: 4.06 | K12: 6.59 | L12: N | M12: Y
A13: PRD00012 | B13: CC-0012 | C13: Fresh Dairy Item 012 | D13: Fresh Dairy | E13: Kg | F13: SUP00014 | G13: 2 | H13: 6 | I13: 21 | J13: 3.14 | K13: 4.7 | L13: Y | M13: Y
... A181: PRD00180 | B181: CC-0180 | C181: Frozen Dessert Item 180 | D181: Frozen Dessert | E181: Pack | F181: SUP00110 | G181: -18 | H181: -10 | I181: 10 | J181: 14.43 | K181: 34.18 | L181: Y | M181: Y

Sheet purchase_orders_coldchain
A1: po_id | B1: supplier_id | C1: warehouse_id | D1: warehouse_name | E1: order_date | F1: expected_delivery_date | G1: status | H1: ordered_by | I1: currency | J1: shipping_cost | K1: priority
A2: PO000001 | B2: SUP00061 | C2: WH-ABJ-01 | D2: Abuja Distribution Hub | E2: 45685.255 | F2: 45690.255 | G2: Cancelled | H2: A. Yusuf | I2: NGN | J2: 52.81 | K2: Normal
A3: PO000002 | B3: SUP00101 | C3: WH-LAG-01 | D3: Lagos North Cold Hub | E3: 45675.255 | F3: 45677.255 | G3: Open | H3: I. Chukwu | I3: NGN | J3: 170.13 | K3: Normal
A4: PO000003 | B4: SUP00089 | C4: WH-AWK-01 | D4: Awka Micro Hub | E4: 45660.737 | F4: 45668.737 | G4: Partial | H4: I. Chukwu | I4: USD | J4: 175.86 | K4: Normal
A5: PO000004 | B5: SUP00004 | C5: WH-JOS-01 | D5: Jos Altitude Hub | E5: 45668.691 | F5: 45686.691 | G5: Received | H5: T. Bello | I5: NGN | J5: 159.19 | K5: Normal
A6: PO000005 | B6: SUP00059 | C6: WH-LAG-02 | D6: Lagos South Cold Hub | E6: 45686.325 | F6: 45691.325 | G6: Received | H6: M. Okafor | I6: NGN | J6: 298.77 | K6: Normal
A7: PO000006 | B7: SUP00077 | C7: WH-BEN-01 | D7: Benin City Hub | E7: 45711.177 | F7: 45722.177 | G7: Cancelled | H7: S. Ibrahim | I7: NGN | J7: 191.67 | K7: Normal
A8: PO000007 | B8: SUP00079 | C8: WH-ABJ-01 | D8: Abuja Distribution Hub | E8: 45719.591 | F8: 45731.591 | G8: Received | H8: A. Yusuf | I8: NGN | J8: 176.05 | K8: Urgent
A9: PO000008 | B9: SUP00083 | C9: WH-ABJ-01 | D9: Abuja Distribution Hub | E9: 45666.835 | F9: 45684.835 | G9: Partial | H9: S. Ibrahim | I9: NGN | J9: 88.26 | K9: Normal
A10: PO000009 | B10: SUP00051 | C10: WH-LAG-01 | D10: Lagos North Cold Hub | E10: 45659.464 | F10: 45679.464 | G10: Received | H10: I. Chukwu | I10: USD | J10: 165.31 | K10: Urgent
A11: PO000010 | B11: SUP00048 | C11: WH-ENU-01 | D11: Enugu Regional Hub | E11: 45667.774 | F11: 45675.774 | G11: Received | H11: T. Bello | I11: NGN | J11: 275.54 | K11: Normal
A12: PO000011 | B12: SUP00043 | C12: WH-IBA-01 | D12: Ibadan Regional Hub | E12: 45700.061 | F12: 45705.061 | G12: Open | H12: M. Okafor | I12: NGN | J12: 239.87 | K12: Urgent
A13: PO000012 | B13: SUP00027 | C13: WH-ABJ-01 | D13: Abuja Distribution Hub | E13: 45703.656 | F13: 45707.656 | G13: Partial | H13: S. Ibrahim | I13: NGN | J13: 157.83 | K13: Urgent
... A151: PO000150 | B151: SUP00117 | C151: WH-BEN-01 | D151: Benin City Hub | E151: 45681.339 | F151: 45690.339 | G151: Received | H151: T. Bello | I151: USD | J151: 45.24 | K151: Normal

Sheet purchase_order_lines_coldchain
A1: po_line_id | B1: po_id | C1: supplier_id | D1: warehouse_id | E1: order_date | F1: expected_delivery_date | G1: product_id | H1: ordered_qty | I1: unit_cost | J1: discount_pct | K1: line_total | L1: line_total_actual | M1: line_total_Check | N1: line_status
A2: POL000001 | B2: PO000001 | C2: SUP00061 | D2: WH-ABJ-01 | E2: 45685.255 | F2: 45690.255 | G2: PRD00161 | H2: 85 | I2: 3.75 | J2: 2.5 | K2: 310.78 | L2: =ROUND((H2*I2)-(J2/100)*(H2*I2),2) -> 310.78 | M2: =IF(K2=L2,"Pass",IF(K2=L2-0.01,"Pass","Investigate")) -> Pass | N2: Open
A3: POL000002 | B3: PO000001 | C3: SUP00061 | D3: WH-ABJ-01 | E3: 45685.255 | F3: 45690.255 | G3: PRD00161 | H3: 96 | I3: 3.57 | J3: 0 | K3: 342.72 | L3: =ROUND((H3*I3)-(J3/100)*(H3*I3),2) -> 342.72 | M3: =IF(K3=L3,"Pass",IF(K3=L3-0.01,"Pass","Investigate")) -> Pass | N3: Open
A4: POL000003 | B4: PO000001 | C4: SUP00061 | D4: WH-ABJ-01 | E4: 45685.255 | F4: 45690.255 | G4: PRD00161 | H4: 169 | I4: 4.05 | J4: 0 | K4: 684.45 | L4: =ROUND((H4*I4)-(J4/100)*(H4*I4),2) -> 684.45 | M4: =IF(K4=L4,"Pass",IF(K4=L4-0.01,"Pass","Investigate")) -> Pass | N4: Closed
A5: POL000004 | B5: PO000002 | C5: SUP00101 | D5: WH-LAG-01 | E5: 45675.255 | F5: 45677.255 | G5: PRD00067 | H5: 144 | I5: 2.42 | J5: 5 | K5: 331.06 | L5: =ROUND((H5*I5)-(J5/100)*(H5*I5),2) -> 331.06 | M5: =IF(K5=L5,"Pass",IF(K5=L5-0.01,"Pass","Investigate")) -> Pass | N5: Open
A6: POL000005 | B6: PO000002 | C6: SUP00101 | D6: WH-LAG-01 | E6: 45675.255 | F6: 45677.255 | G6: PRD00033 | H6: 237 | I6: 13.16 | J6: 0 | K6: 3118.92 | L6: =ROUND((H6*I6)-(J6/100)*(H6*I6),2) -> 3118.92 | M6: =IF(K6=L6,"Pass",IF(K6=L6-0.01,"Pass","Investigate")) -> Pass | N6: Open
A7: POL000006 | B7: PO000003 | C7: SUP00089 | D7: WH-AWK-01 | E7: 45660.737 | F7: 45668.737 | G7: PRD00178 | H7: 64 | I7: 3.96 | J7: 7.5 | K7: 234.43 | L7: =ROUND((H7*I7)-(J7/100)*(H7*I7),2) -> 234.43 | M7: =IF(K7=L7,"Pass",IF(K7=L7-0.01,"Pass","Investigate")) -> Pass | N7: Open
A8: POL000007 | B8: PO000003 | C8: SUP00089 | D8: WH-AWK-01 | E8: 45660.737 | F8: 45668.737 | G8: PRD00011 | H8: 156 | I8: 4.15 | J8: 10 | K8: 582.66 | L8: =ROUND((H8*I8)-(J8/100)*(H8*I8),2) -> 582.66 | M8: =IF(K8=L8,"Pass",IF(K8=L8-0.01,"Pass","Investigate")) -> Pass | N8: Open
A9: POL000008 | B9: PO000004 | C9: SUP00004 | D9: WH-JOS-01 | E9: 45668.691 | F9: 45686.691 | G9: PRD00007 | H9: 105 | I9: 13.26 | J9: 0 | K9: 1392.3 | L9: =ROUND((H9*I9)-(J9/100)*(H9*I9),2) -> 1392.3 | M9: =IF(K9=L9,"Pass",IF(K9=L9-0.01,"Pass","Investigate")) -> Pass | N9: Closed
A10: POL000009 | B10: PO000004 | C10: SUP00004 | D10: WH-JOS-01 | E10: 45668.691 | F10: 45686.691 | G10: PRD00058 | H10: 104 | I10: 6.88 | J10: 0 | K10: 715.52 | L10: =ROUND((H10*I10)-(J10/100)*(H10*I10),2) -> 715.52 | M10: =IF(K10=L10,"Pass",IF(K10=L10-0.01,"Pass","Investigate")) -> Pass | N10: Closed
A11: POL000010 | B11: PO000004 | C11: SUP00004 | D11: WH-JOS-01 | E11: 45668.691 | F11: 45686.691 | G11: PRD00141 | H11: 96 | I11: 10.54 | J11: 10 | K11: 910.66 | L11: =ROUND((H11*I11)-(J11/100)*(H11*I11),2) -> 910.66 | M11: =IF(K11=L11,"Pass",IF(K11=L11-0.01,"Pass","Investigate")) -> Pass | N11: Partial
A12: POL000011 | B12: PO000005 | C12: SUP00059 | D12: WH-LAG-02 | E12: 45686.325 | F12: 45691.325 | G12: PRD00170 | H12: 29 | I12: 9.98 | J12: 10 | K12: 260.48 | L12: =ROUND((H12*I12)-(J12/100)*(H12*I12),2) -> 260.48 | M12: =IF(K12=L12,"Pass",IF(K12=L12-0.01,"Pass","Investigate")) -> Pass | N12: Partial
A13: POL000012 | B13: PO000005 | C13: SUP00059 | D13: WH-LAG-02 | E13: 45686.325 | F13: 45691.325 | G13: PRD00147 | H13: 130 | I13: 16.2 | J13: 10 | K13: 1895.4 | L13: =ROUND((H13*I13)-(J13/100)*(H13*I13),2) -> 1895.4 | M13: =IF(K13=L13,"Pass",IF(K13=L13-0.01,"Pass","Investigate")) -> Pass | N13: Closed
... A421: POL000420 | B421: PO000150 | C421: SUP00117 | D421: WH-BEN-01 | E421: 45681.339 | F421: 45690.339 | G421: PRD00064 | H421: 123 | I421: 2.8 | J421: 10 | K421: 309.96 | L421: =ROUND((H421*I421)-(J421/100)*(H421*I421),2) -> 309.96 | M421: =IF(K421=L421,"Pass",IF(K421=L421-0.01,"Pass","Investigate")) -> Pass | N421: Open

Sheet stock_movements_coldchain
A1: movement_id | B1: movement_date | C1: movement_type | D1: warehouse_id | E1: product_id | F1: po_line_id | G1: reference_id | H1: missing_reference_id_check | I1: reference_id_actual | J1: lot_number | K1: quantity | L1: signed_qty | M1: unit_cost | N1: movement_value | O1: temperature_c | P1: reason
A2: MOV0000001 | B2: 45719.491 | C2: Receipt | D2: WH-PHC-01 | E2: PRD00124 | F2: POL000312 | G2: PO000111 | H2: {=IF(AND(G2="", C2="Receipt"), _xlfn.XLOOKUP(1, (purchase_order_lines_coldchain!A2:A1000 = F2) * (purchase_order_lines_coldchain!G2:G1000 = E2) * (purchase_order_lines_coldchain!D2:D1000 = D2), purchase_order_lines_coldchain!B$2:B$1000, _xlfn.XLOOKUP(F2,purchase_order_lines_coldchain!A$2:A1000, purchase_order_lines_coldchain!B$2:B1000)), "")} | I2: =G2 & H2 -> PO000111 | J2: LOT-124-000001 | K2: 89 | L2: 89 | M2: 15.19 | N2: 1351.91 | O2: 0.8 | P2: Supplier_Delivery
A3: MOV0000002 | B3: 45725.942 | C3: Receipt | D3: WH-ENU-01 | E3: PRD00043 | F3: POL000073 | G3: PO000026 | H3: {=IF(AND(G3="", C3="Receipt"), _xlfn.XLOOKUP(1, (purchase_order_lines_coldchain!A3:A1001 = F3) * (purchase_order_lines_coldchain!G3:G1001 = E3) * (purchase_order_lines_coldchain!D3:D1001 = D3), purchase_order_lines_coldchain!B$2:B$1000, _xlfn.XLOOKUP(F3,purchase_order_lines_coldchain!A$2:A1001, purchase_order_lines_coldchain!B$2:B1001)), "")} | I3: =G3 & H3 -> PO000026 | J3: LOT-043-000002 | K3: 148 | L3: 148 | M3: 13 | N3: 1924 | O3: 4.5 | P3: Supplier_Delivery
A4: MOV0000003 | B4: 45706.944 | C4: Receipt | D4: WH-AWK-01 | E4: PRD00075 | F4: POL000128 | G4: PO000046 | H4: {=IF(AND(G4="", C4="Receipt"), _xlfn.XLOOKUP(1, (purchase_order_lines_coldchain!A4:A1002 = F4) * (purchase_order_lines_coldchain!G4:G1002 = E4) * (purchase_order_lines_coldchain!D4:D1002 = D4), purchase_order_lines_coldchain!B$2:B$1000, _xlfn.XLOOKUP(F4,purchase_order_lines_coldchain!A$2:A1002, purchase_order_lines_coldchain!B$2:B1002)), "")} | I4: =G4 & H4 -> PO000046 | J4: LOT-075-000003 | K4: 44 | L4: 44 | M4: 11.87 | N4: 522.28 | O4: 7.6 | P4: Supplier_Delivery
A5: MOV0000004 | B5: 45733.142 | C5: Receipt | D5: WH-PHC-01 | E5: PRD00066 | F5: POL000138 | G5: PO000050 | H5: {=IF(AND(G5="", C5="Receipt"), _xlfn.XLOOKUP(1, (purchase_order_lines_coldchain!A5:A1003 = F5) * (purchase_order_lines_coldchain!G5:G1003 = E5) * (purchase_order_lines_coldchain!D5:D1003 = D5), purchase_order_lines_coldchain!B$2:B$1000, _xlfn.XLOOKUP(F5,purchase_order_lines_coldchain!A$2:A1003, purchase_order_lines_coldchain!B$2:B1003)), "")} | I5: =G5 & H5 -> PO000050 | J5: LOT-066-000004 | K5: 181 | L5: 181 | M5: 4.88 | N5: 883.28 | O5: 6 | P5: Supplier_Delivery
A6: MOV0000005 | B6: 45711.088 | C6: Receipt | D6: WH-ENU-01 | E6: PRD00066 | F6: POL000156 | G6: PO000056 | H6: {=IF(AND(G6="", C6="Receipt"), _xlfn.XLOOKUP(1, (purchase_order_lines_coldchain!A6:A1004 = F6) * (purchase_order_lines_coldchain!G6:G1004 = E6) * (purchase_order_lines_coldchain!D6:D1004 = D6), purchase_order_lines_coldchain!B$2:B$1000, _xlfn.XLOOKUP(F6,purchase_order_lines_coldchain!A$2:A1004, purchase_order_lines_coldchain!B$2:B1004)), "")} | I6: =G6 & H6 -> PO000056 | J6: LOT-066-000005 | K6: 117 | L6: 117 | M6: 4.58 | N6: 535.86 | O6: 7.6 | P6: Supplier_Delivery
A7: MOV0000006 | B7: 45671.68 | C7: Receipt | D7: WH-ENU-01 | E7: PRD00011 | F7: POL000151 | G7: PO000054 | H7: {=IF(AND(G7="", C7="Receipt"), _xlfn.XLOOKUP(1, (purchase_order_lines_coldchain!A7:A1005 = F7) * (purchase_order_lines_coldchain!G7:G1005 = E7) * (purchase_order_lines_coldchain!D7:D1005 = D7), purchase_order_lines_coldchain!B$2:B$1000, _xlfn.XLOOKUP(F7,purchase_order_lines_coldchain!A$2:A1005, purchase_order_lines_coldchain!B$2:B1005)), "")} | I7: =G7 & H7 -> PO000054 | J7: LOT-011-000006 | K7: 42 | L7: 42 | M7: 3.97 | N7: 166.74 | O7: 4.8 | P7: Supplier_Delivery
A8: MOV0000007 | B8: 45709.894 | C8: Receipt | D8: WH-PHC-01 | E8: PRD00107 | F8: POL000289 | G8: PO000103 | H8: {=IF(AND(G8="", C8="Receipt"), _xlfn.XLOOKUP(1, (purchase_order_lines_coldchain!A8:A1006 = F8) * (purchase_order_lines_coldchain!G8:G1006 = E8) * (purchase_order_lines_coldchain!D8:D1006 = D8), purchase_order_lines_coldchain!B$2:B$1000, _xlfn.XLOOKUP(F8,purchase_order_lines_coldchain!A$2:A1006, purchase_order_lines_coldchain!B$2:B1006)), "")} | I8: =G8 & H8 -> PO000103 | J8: LOT-107-000007 | K8: 47 | L8: 47 | M8: 11.56 | N8: 543.32 | O8: 2.8 | P8: Supplier_Delivery
A9: MOV0000008 | B9: 45707.269 | C9: Receipt | D9: WH-IBA-01 | E9: PRD00118 | F9: POL000028 | G9: PO000011 | H9: {=IF(AND(G9="", C9="Receipt"), _xlfn.XLOOKUP(1, (purchase_order_lines_coldchain!A9:A1007 = F9) * (purchase_order_lines_coldchain!G9:G1007 = E9) * (purchase_order_lines_coldchain!D9:D1007 = D9), purchase_order_lines_coldchain!B$2:B$1000, _xlfn.XLOOKUP(F9,purchase_order_lines_coldchain!A$2:A1007, purchase_order_lines_coldchain!B$2:B1007)), "")} | I9: =G9 & H9 -> PO000011 | J9: LOT-118-000008 | K9: 123 | L9: 123 | M9: 10.55 | N9: 1297.65 | O9: 7.8 | P9: Supplier_Delivery
A10: MOV0000009 | B10: 45679.232 | C10: Receipt | D10: WH-KAD-01 | E10: PRD00080 | F10: POL000162 | G10: PO000058 | H10: {=IF(AND(G10="", C10="Receipt"), _xlfn.XLOOKUP(1, (purchase_order_lines_coldchain!A10:A1008 = F10) * (purchase_order_lines_coldchain!G10:G1008 = E10) * (purchase_order_lines_coldchain!D10:D1008 = D10), purchase_order_lines_coldchain!B$2:B$1000, _xlfn.XLOOKUP(F10,purchase_order_lines_coldchain!A$2:A1008, purchase_order_lines_coldchain!B$2:B1008)), "")} | I10: =G10 & H10 -> PO000058 | J10: LOT-080-000009 | K10: 209 | L10: 209 | M10: 6.77 | N10: 1414.93 | O10: 6.6 | P10: Supplier_Delivery
A11: MOV0000010 | B11: 45701.304 | C11: Receipt | D11: WH-IBA-01 | E11: PRD00144 | F11: POL000327 | G11: PO000116 | H11: {=IF(AND(G11="", C11="Receipt"), _xlfn.XLOOKUP(1, (purchase_order_lines_coldchain!A11:A1009 = F11) * (purchase_order_lines_coldchain!G11:G1009 = E11) * (purchase_order_lines_coldchain!D11:D1009 = D11), purchase_order_lines_coldchain!B$2:B$1000, _xlfn.XLOOKUP(F11,purchase_order_lines_coldchain!A$2:A1009, purchase_order_lines_coldchain!B$2:B1009)), "")} | I11: =G11 & H11 -> PO000116 | J11: LOT-144-000010 | K11: 88 | L11: 88 | M11: 14.25 | N11: 1254 | O11: 1.4 | P11: Supplier_Delivery
A12: MOV0000011 | B12: 45679.886 | C12: Receipt | D12: WH-ABJ-01 | E12: PRD00128 | F12: POL000297 | G12: PO000105 | H12: {=IF(AND(G12="", C12="Receipt"), _xlfn.XLOOKUP(1, (purchase_order_lines_coldchain!A12:A1010 = F12) * (purchase_order_lines_coldchain!G12:G1010 = E12) * (purchase_order_lines_coldchain!D12:D1010 = D12), purchase_order_lines_coldchain!B$2:B$1000, _xlfn.XLOOKUP(F12,purchase_order_lines_coldchain!A$2:A1010, purchase_order_lines_coldchain!B$2:B1010)), "")} | I12: =G12 & H12 -> PO000105 | J12: LOT-128-000011 | K12: 121 | L12: 121 | M12: 11.92 | N12: 1442.32 | O12: 5.8 | P12: Supplier_Delivery
A13: MOV0000012 | B13: 45709.019 | C13: Receipt | D13: WH-PHC-01 | E13: PRD00022 | F13: POL000291 | G13: PO000103 | H13: {=IF(AND(G13="", C13="Receipt"), _xlfn.XLOOKUP(1, (purchase_order_lines_coldchain!A13:A1011 = F13) * (purchase_order_lines_coldchain!G13:G1011 = E13) * (purchase_order_lines_coldchain!D13:D1011 = D13), purchase_order_lines_coldchain!B$2:B$1000, _xlfn.XLOOKUP(F13,purchase_order_lines_coldchain!A$2:A1011, purchase_order_lines_coldchain!B$2:B1011)), "")} | I13: =G13 & H13 -> PO000103 | J13: LOT-022-000012 | K13: 234 | L13: 234 | M13: 1.81 | N13: 423.54 | O13: 3.7 | P13: Supplier_Delivery
... A53: MOV0000052 | B53: 45732.777 | C53: Receipt | D53: WH-LAG-01 | E53: PRD00070 | F53: POL000399 | G53: PO000143 | H53: {=IF(AND(G53="", C53="Receipt"), _xlfn.XLOOKUP(1, (purchase_order_lines_coldchain!A53:A1051 = F53) * (purchase_order_lines_coldchain!G53:G1051 = E53) * (purchase_order_lines_coldchain!D53:D1051 = D53), purchase_order_lines_coldchain!B$2:B$1000, _xlfn.XLOOKUP(F53,purchase_order_lines_coldchain!A$2:A1051, purchase_order_lines_coldchain!B$2:B1051)), "")} | I53: =G53 & H53 -> PO000143 | J53: LOT-070-000052 | K53: 148 | L53: 148 | M53: 5.95 | N53: 880.6 | O53: 0.9 | P53: Supplier_Delivery
A54: MOV0000053 | B54: 45739.14 | C54: Receipt | D54: WH-ABJ-01 | E54: PRD00067 | F54: POL000181 | H54: {=IF(AND(G54="", C54="Receipt"), _xlfn.XLOOKUP(1, (purchase_order_lines_coldchain!A54:A1052 = F54) * (purchase_order_lines_coldchain!G54:G1052 = E54) * (purchase_order_lines_coldchain!D54:D1052 = D54), purchase_order_lines_coldchain!B$2:B$1000, _xlfn.XLOOKUP(F54,purchase_order_lines_coldchain!A$2:A1052, purchase_order_lines_coldchain!B$2:B1052)), "")} -> PO000047 | I54: =G54 & H54 -> PO000047 | J54: LOT-067-000053 | K54: 126 | L54: 126 | M54: 2.58 | N54: 325.08 | O54: 4.9 | P54: Supplier_Delivery
A55: MOV0000054 | B55: 45738.846 | C55: Receipt | D55: WH-ENU-01 | E55: PRD00018 | F55: POL000333 | G55: PO000118 | H55: {=IF(AND(G55="", C55="Receipt"), _xlfn.XLOOKUP(1, (purchase_order_lines_coldchain!A55:A1053 = F55) * (purchase_order_lines_coldchain!G55:G1053 = E55) * (purchase_order_lines_coldchain!D55:D1053 = D55), purchase_order_lines_coldchain!B$2:B$1000, _xlfn.XLOOKUP(F55,purchase_order_lines_coldchain!A$2:A1053, purchase_order_lines_coldchain!B$2:B1053)), "")} | I55: =G55 & H55 -> PO000118 | J55: LOT-018-000054 | K55: 40 | L55: 40 | M55: 12.33 | N55: 493.2 | O55: 3.6 | P55: Supplier_Delivery
A56: MOV0000055 | B56: 45712.733 | C56: Receipt | D56: WH-KAD-01 | E56: PRD00098 | F56: POL000279 | G56: PO000099 | H56: {=IF(AND(G56="", C56="Receipt"), _xlfn.XLOOKUP(1, (purchase_order_lines_coldchain!A56:A1054 = F56) * (purchase_order_lines_coldchain!G56:G1054 = E56) * (purchase_order_lines_coldchain!D56:D1054 = D56), purchase_order_lines_coldchain!B$2:B$1000, _xlfn.XLOOKUP(F56,purchase_order_lines_coldchain!A$2:A1054, purchase_order_lines_coldchain!B$2:B1054)), "")} | I56: =G56 & H56 -> PO000099 | J56: LOT-098-000055 | K56: 11 | L56: 11 | M56: 1.8 | N56: 19.8 | O56: 7.7 | P56: Supplier_Delivery
A57: MOV0000056 | B57: 45711.858 | C57: Receipt | D57: WH-KAD-01 | E57: PRD00098 | F57: POL000281 | G57: PO000099 | H57: {=IF(AND(G57="", C57="Receipt"), _xlfn.XLOOKUP(1, (purchase_order_lines_coldchain!A57:A1055 = F57) * (purchase_order_lines_coldchain!G57:G1055 = E57) * (purchase_order_lines_coldchain!D57:D1055 = D57), purchase_order_lines_coldchain!B$2:B$1000, _xlfn.XLOOKUP(F57,purchase_order_lines_coldchain!A$2:A1055, purchase_order_lines_coldchain!B$2:B1055)), "")} | I57: =G57 & H57 -> PO000099 | J57: LOT-098-000056 | K57: 56 | L57: 56 | M57: 1.74 | N57: 97.44 | O57: 3.7 | P57: Supplier_Delivery
A58: MOV0000057 | B58: 45691.505 | C58: Receipt | D58: WH-ABJ-01 | E58: PRD00161 | F58: POL000001 | G58: PO000001 | H58: {=IF(AND(G58="", C58="Receipt"), _xlfn.XLOOKUP(1, (purchase_order_lines_coldchain!A58:A1056 = F58) * (purchase_order_lines_coldchain!G58:G1056 = E58) * (purchase_order_lines_coldchain!D58:D1056 = D58), purchase_order_lines_coldchain!B$2:B$1000, _xlfn.XLOOKUP(F58,purchase_order_lines_coldchain!A$2:A1056, purchase_order_lines_coldchain!B$2:B1056)), "")} | I58: =G58 & H58 -> PO000001 | J58: LOT-161-000057 | K58: 84 | L58: 84 | M58: 3.75 | N58: 315 | O58: 2.6 | P58: Supplier_Delivery
A59: MOV0000058 | B59: 45721.409 | C59: Receipt | D59: WH-BEN-01 | E59: PRD00146 | F59: POL000186 | G59: PO000066 | H59: {=IF(AND(G59="", C59="Receipt"), _xlfn.XLOOKUP(1, (purchase_order_lines_coldchain!A59:A1057 = F59) * (purchase_order_lines_coldchain!G59:G1057 = E59) * (purchase_order_lines_coldchain!D59:D1057 = D59), purchase_order_lines_coldchain!B$2:B$1000, _xlfn.XLOOKUP(F59,purchase_order_lines_coldchain!A$2:A1057, purchase_order_lines_coldchain!B$2:B1057)), "")} | I59: =G59 & H59 -> PO000066 | J59: LOT-146-000058 | K59: 106 | L59: 106 | M59: 8.46 | N59: 896.76 | O59: 4.1 | P59: Supplier_Delivery
A60: MOV0000059 | B60: 45712.856 | C60: Receipt | D60: WH-ENU-01 | E60: PRD00054 | F60: POL000339 | G60: PO000120 | H60: {=IF(AND(G60="", C60="Receipt"), _xlfn.XLOOKUP(1, (purchase_order_lines_coldchain!A60:A1058 = F60) * (purchase_order_lines_coldchain!G60:G1058 = E60) * (purchase_order_lines_coldchain!D60:D1058 = D60), purchase_order_lines_coldchain!B$2:B$1000, _xlfn.XLOOKUP(F60,purchase_order_lines_coldchain!A$2:A1058, purchase_order_lines_coldchain!B$2:B1058)), "")} | I60: =G60 & H60 -> PO000120 | J60: LOT-054-000059 | K60: 53 | L60: 53 | M60: 1.61 | N60: 85.33 | O60: 5.3 | P60: Supplier_Delivery
A61: MOV0000060 | B61: 45728.248 | C61: Receipt | D61: WH-KAD-01 | E61: PRD00136 | F61: POL000115 | G61: PO000042 | H61: {=IF(AND(G61="", C61="Receipt"), _xlfn.XLOOKUP(1, (purchase_order_lines_coldchain!A61:A1059 = F61) * (purchase_order_lines_coldchain!G61:G1059 = E61) * (purchase_order_lines_coldchain!D61:D1059 = D61), purchase_order_lines_coldchain!B$2:B$1000, _xlfn.XLOOKUP(F61,purchase_order_lines_coldchain!A$2:A1059, purchase_order_lines_coldchain!B$2:B1059)), "")} | I61: =G61 & H61 -> PO000042 | J61: LOT-136-000060 | K61: 163 | L61: 163 | M61: 5.64 | N61: 919.32 | O61: 4.6 | P61: Supplier_Delivery
A62: MOV0000061 | B62: 45733.653 | C62: Receipt | D62: WH-LAG-02 | E62: PRD00005 | F62: POL000112 | G62: PO000041 | H62: {=IF(AND(G62="", C62="Receipt"), _xlfn.XLOOKUP(1, (purchase_order_lines_coldchain!A62:A1060 = F62) * (purchase_order_lines_coldchain!G62:G1060 = E62) * (purchase_order_lines_coldchain!D62:D1060 = D62), purchase_order_lines_coldchain!B$2:B$1000, _xlfn.XLOOKUP(F62,purchase_order_lines_coldchain!A$2:A1060, purchase_order_lines_coldchain!B$2:B1060)), "")} | I62: =G62 & H62 -> PO000041 | J62: LOT-005-000061 | K62: 67 | L62: 67 | M62: 2.15 | N62: 144.05 | O62: 3 | P62: Supplier_Delivery
A63: MOV0000062 | B63: 45668.778 | C63: Receipt | D63: WH-AWK-01 | E63: PRD00178 | F63: POL000006 | G63: PO000003 | H63: {=IF(AND(G63="", C63="Receipt"), _xlfn.XLOOKUP(1, (purchase_order_lines_coldchain!A63:A1061 = F63) * (purchase_order_lines_coldchain!G63:G1061 = E63) * (purchase_order_lines_coldchain!D63:D1061 = D63), purchase_order_lines_coldchain!B$2:B$1000, _xlfn.XLOOKUP(F63,purchase_order_lines_coldchain!A$2:A1061, purchase_order_lines_coldchain!B$2:B1061)), "")} | I63: =G63 & H63 -> PO000003 | J63: LOT-178-000062 | K63: 49 | L63: 49 | M63: 3.96 | N63: 194.04 | O63: 3.5 | P63: Supplier_Delivery
A64: MOV0000063 | B64: 45665.183 | C64: Receipt | D64: WH-ENU-01 | E64: PRD00039 | F64: POL000106 | G64: PO000039 | H64: {=IF(AND(G64="", C64="Receipt"), _xlfn.XLOOKUP(1, (purchase_order_lines_coldchain!A64:A1062 = F64) * (purchase_order_lines_coldchain!G64:G1062 = E64) * (purchase_order_lines_coldchain!D64:D1062 = D64), purchase_order_lines_coldchain!B$2:B$1000, _xlfn.XLOOKUP(F64,purchase_order_lines_coldchain!A$2:A1062, purchase_order_lines_coldchain!B$2:B1062)), "")} | I64: =G64 & H64 -> PO000039 | J64: LOT-039-000063 | K64: 178 | L64: 178 | M64: 4.74 | N64: 843.72 | O64: 1.8 | P64: Supplier_Delivery
A65: MOV0000064 | B65: 45678.658 | C65: Receipt | D65: WH-ABJ-01 | E65: PRD00098 | F65: POL000141 | G65: PO000051 | H65: {=IF(AND(G65="", C65="Receipt"), _xlfn.XLOOKUP(1, (purchase_order_lines_coldchain!A65:A1063 = F65) * (purchase_order_lines_coldchain!G65:G1063 = E65) * (purchase_order_lines_coldchain!D65:D1063 = D65), purchase_order_lines_coldchain!B$2:B$1000, _xlfn.XLOOKUP(F65,purchase_order_lines_coldchain!A$2:A1063, purchase_order_lines_coldchain!B$2:B1063)), "")} | I65: =G65 & H65 -> PO000051 | J65: LOT-098-000064 | K65: 104 | L65: 104 | M65: 1.77 | N65: 184.08 | O65: 5.5 | P65: Supplier_Delivery
A66: MOV0000065 | B66: 45675.423 | C66: Receipt | D66: WH-ENU-01 | E66: PRD00086 | F66: POL000078 | G66: PO000028 | H66: {=IF(AND(G66="", C66="Receipt"), _xlfn.XLOOKUP(1, (purchase_order_lines_coldchain!A66:A1064 = F66) * (purchase_order_lines_coldchain!G66:G1064 = E66) * (purchase_order_lines_coldchain!D66:D1064 = D66), purchase_order_lines_coldchain!B$2:B$1000, _xlfn.XLOOKUP(F66,purchase_order_lines_coldchain!A$2:A1064, purchase_order_lines_coldchain!B$2:B1064)), "")} | I66: =G66 & H66 -> PO000028 | J66: LOT-086-000065 | K66: 117 | L66: 117 | M66: 5.46 | N66: 638.82 | O66: 7.5 | P66: Supplier_Delivery
... A150: MOV0000149 | B150: 45718.148 | C150: Receipt | D150: WH-ABJ-01 | E150: PRD00051 | F150: POL000317 | G150: PO000113 | H150: {=IF(AND(G150="", C150="Receipt"), _xlfn.XLOOKUP(1, (purchase_order_lines_coldchain!A150:A1148 = F150) * (purchase_order_lines_coldchain!G150:G1148 = E150) * (purchase_order_lines_coldchain!D150:D1148 = D150), purchase_order_lines_coldchain!B$2:B$1000, _xlfn.XLOOKUP(F150,purchase_order_lines_coldchain!A$2:A1148, purchase_order_lines_coldchain!B$2:B1148)), "")} | I150: =G150 & H150 -> PO000113 | J150: LOT-051-000149 | K150: 152 | L150: 152 | M150: 1.79 | N150: 272.08 | O150: 7.2 | P150: Supplier_Delivery
A151: MOV0000150 | B151: 45699.84 | C151: Receipt | D151: WH-BEN-01 | E151: PRD00105 | F151: POL000284 | H151: {=IF(AND(G151="", C151="Receipt"), _xlfn.XLOOKUP(1, (purchase_order_lines_coldchain!A151:A1149 = F151) * (purchase_order_lines_coldchain!G151:G1149 = E151) * (purchase_order_lines_coldchain!D151:D1149 = D151), purchase_order_lines_coldchain!B$2:B$1000, _xlfn.XLOOKUP(F151,purchase_order_lines_coldchain!A$2:A1149, purchase_order_lines_coldchain!B$2:B1149)), "")} -> PO000049 | I151: =G151 & H151 -> PO000049 | J151: LOT-105-000150 | K151: 198 | L151: 198 | M151: 8.95 | N151: 1772.1 | O151: 3.4 | P151: Supplier_Delivery
A152: MOV0000151 | B152: 45713.947 | C152: Receipt | D152: WH-LAG-02 | E152: PRD00070 | F152: POL000101 | G152: PO000037 | H152: {=IF(AND(G152="", C152="Receipt"), _xlfn.XLOOKUP(1, (purchase_order_lines_coldchain!A152:A1150 = F152) * (purchase_order_lines_coldchain!G152:G1150 = E152) * (purchase_order_lines_coldchain!D152:D1150 = D152), purchase_order_lines_coldchain!B$2:B$1000, _xlfn.XLOOKUP(F152,purchase_order_lines_coldchain!A$2:A1150, purchase_order_lines_coldchain!B$2:B1150)), "")} | I152: =G152 & H152 -> PO000037 | J152: LOT-070-000151 | K152: 136 | L152: 136 | M152: 5.86 | N152: 796.96 | O152: 8.5 | P152: Supplier_Delivery
A153: MOV0000152 | B153: 45721.933 | C153: Receipt | D153: WH-IBA-01 | E153: PRD00163 | F153: POL000058 | G153: PO000021 | H153: {=IF(AND(G153="", C153="Receipt"), _xlfn.XLOOKUP(1, (purchase_order_lines_coldchain!A153:A1151 = F153) * (purchase_order_lines_coldchain!G153:G1151 = E153) * (purchase_order_lines_coldchain!D153:D1151 = D153), purchase_order_lines_coldchain!B$2:B$1000, _xlfn.XLOOKUP(F153,purchase_order_lines_coldchain!A$2:A1151, purchase_order_lines_coldchain!B$2:B1151)), "")} | I153: =G153 & H153 -> PO000021 | J153: LOT-163-000152 | K153: 18 | L153: 18 | M153: 8.24 | N153: 148.32 | O153: 5.4 | P153: Supplier_Delivery
A154: MOV0000153 | B154: 45701.203 | C154: Receipt | D154: WH-PHC-01 | E154: PRD00051 | F154: POL000134 | G154: PO000049 | H154: {=IF(AND(G154="", C154="Receipt"), _xlfn.XLOOKUP(1, (purchase_order_lines_coldchain!A154:A1152 = F154) * (purchase_order_lines_coldchain!G154:G1152 = E154) * (purchase_order_lines_coldchain!D154:D1152 = D154), purchase_order_lines_coldchain!B$2:B$1000, _xlfn.XLOOKUP(F154,purchase_order_lines_coldchain!A$2:A1152, purchase_order_lines_coldchain!B$2:B1152)), "")} | I154: =G154 & H154 -> PO000049 | J154: LOT-051-000153 | K154: 89 | L154: 89 | M154: 1.71 | N154: 152.19 | O154: 6.9 | P154: Supplier_Delivery
A155: MOV0000154 | B155: 45742.193 | C155: Receipt | D155: WH-ENU-01 | E155: PRD00154 | F155: POL000100 | G155: PO000036 | H155: {=IF(AND(G155="", C155="Receipt"), _xlfn.XLOOKUP(1, (purchase_order_lines_coldchain!A155:A1153 = F155) * (purchase_order_lines_coldchain!G155:G1153 = E155) * (purchase_order_lines_coldchain!D155:D1153 = D155), purchase_order_lines_coldchain!B$2:B$1000, _xlfn.XLOOKUP(F155,purchase_order_lines_coldchain!A$2:A1153, purchase_order_lines_coldchain!B$2:B1153)), "")} | I155: =G155 & H155 -> PO000036 | J155: LOT-154-000154 | K155: 211 | L155: 211 | M155: 15.77 | N155: 3327.47 | O155: 1.7 | P155: Supplier_Delivery
A156: MOV0000155 | B156: 45688.302 | C156: Receipt | D156: WH-KAD-01 | E156: PRD00152 | F156: POL000227 | G156: PO000080 | H156: {=IF(AND(G156="", C156="Receipt"), _xlfn.XLOOKUP(1, (purchase_order_lines_coldchain!A156:A1154 = F156) * (purchase_order_lines_coldchain!G156:G1154 = E156) * (purchase_order_lines_coldchain!D156:D1154 = D156), purchase_order_lines_coldchain!B$2:B$1000, _xlfn.XLOOKUP(F156,purchase_order_lines_coldchain!A$2:A1154, purchase_order_lines_coldchain!B$2:B1154)), "")} | I156: =G156 & H156 -> PO000080 | J156: LOT-152-000155 | K156: 30 | L156: 30 | M156: 7.89 | N156: 236.7 | O156: 2.8 | P156: Supplier_Delivery
A157: MOV0000156 | B157: 45709.18 | C157: Receipt | D157: WH-JOS-01 | E157: PRD00134 | F157: POL000080 | G157: PO000029 | H157: {=IF(AND(G157="", C157="Receipt"), _xlfn.XLOOKUP(1, (purchase_order_lines_coldchain!A157:A1155 = F157) * (purchase_order_lines_coldchain!G157:G1155 = E157) * (purchase_order_lines_coldchain!D157:D1155 = D157), purchase_order_lines_coldchain!B$2:B$1000, _xlfn.XLOOKUP(F157,purchase_order_lines_coldchain!A$2:A1155, purchase_order_lines_coldchain!B$2:B1155)), "")} | I157: =G157 & H157 -> PO000029 | J157: LOT-134-000156 | K157: 69 | L157: 69 | M157: 13.34 | N157: 920.46 | O157: 3.4 | P157: Supplier_Delivery
A158: MOV0000157 | B158: 45678.755 | C158: Receipt | D158: WH-LAG-01 | E158: PRD00033 | F158: POL000005 | G158: PO000002 | H158: {=IF(AND(G158="", C158="Receipt"), _xlfn.XLOOKUP(1, (purchase_order_lines_coldchain!A158:A1156 = F158) * (purchase_order_lines_coldchain!G158:G1156 = E158) * (purchase_order_lines_coldchain!D158:D1156 = D158), purchase_order_lines_coldchain!B$2:B$1000, _xlfn.XLOOKUP(F158,purchase_order_lines_coldchain!A$2:A1156, purchase_order_lines_coldchain!B$2:B1156)), "")} | I158: =G158 & H158 -> PO000002 | J158: LOT-033-000157 | K158: 195 | L158: 195 | M158: 13.16 | N158: 2566.2 | O158: 2.3 | P158: Supplier_Delivery
A159: MOV0000158 | B159: 45686.733 | C159: Receipt | D159: WH-ABJ-01 | E159: PRD00055 | F159: POL000219 | G159: PO000078 | H159: {=IF(AND(G159="", C159="Receipt"), _xlfn.XLOOKUP(1, (purchase_order_lines_coldchain!A159:A1157 = F159) * (purchase_order_lines_coldchain!G159:G1157 = E159) * (purchase_order_lines_coldchain!D159:D1157 = D159), purchase_order_lines_coldchain!B$2:B$1000, _xlfn.XLOOKUP(F159,purchase_order_lines_coldchain!A$2:A1157, purchase_order_lines_coldchain!B$2:B1157)), "")} | I159: =G159 & H159 -> PO000078 | J159: LOT-055-000158 | K159: 135 | L159: 135 | M159: 10.66 | N159: 1439.1 | O159: -16 | P159: Supplier_Delivery
A160: MOV0000159 | B160: 45701.297 | C160: Receipt | D160: WH-PHC-01 | E160: PRD00050 | F160: POL000110 | G160: PO000040 | H160: {=IF(AND(G160="", C160="Receipt"), _xlfn.XLOOKUP(1, (purchase_order_lines_coldchain!A160:A1158 = F160) * (purchase_order_lines_coldchain!G160:G1158 = E160) * (purchase_order_lines_coldchain!D160:D1158 = D160), purchase_order_lines_coldchain!B$2:B$1000, _xlfn.XLOOKUP(F160,purchase_order_lines_coldchain!A$2:A1158, purchase_order_lines_coldchain!B$2:B1158)), "")} | I160: =G160 & H160 -> PO000040 | J160: LOT-050-000159 | K160: 87 | L160: 87 | M160: 15.89 | N160: 1382.43 | O160: 0.8 | P160: Supplier_Delivery
A161: MOV0000160 | B161: 45717.562 | C161: Receipt | D161: WH-KAD-01 | E161: PRD00113 | F161: POL000283 | G161: PO000100 | H161: {=IF(AND(G161="", C161="Receipt"), _xlfn.XLOOKUP(1, (purchase_order_lines_coldchain!A161:A1159 = F161) * (purchase_order_lines_coldchain!G161:G1159 = E161) * (purchase_order_lines_coldchain!D161:D1159 = D161), purchase_order_lines_coldchain!B$2:B$1000, _xlfn.XLOOKUP(F161,purchase_order_lines_coldchain!A$2:A1159, purchase_order_lines_coldchain!B$2:B1159)), "")} | I161: =G161 & H161 -> PO000100 | J161: LOT-113-000160 | K161: 224 | L161: 224 | M161: 5.48 | N161: 1227.52 | O161: 3.1 | P161: Supplier_Delivery
A162: MOV0000161 | B162: 45701.284 | C162: Receipt | D162: WH-IBA-01 | E162: PRD00036 | F162: POL000254 | G162: PO000090 | H162: {=IF(AND(G162="", C162="Receipt"), _xlfn.XLOOKUP(1, (purchase_order_lines_coldchain!A162:A1160 = F162) * (purchase_order_lines_coldchain!G162:G1160 = E162) * (purchase_order_lines_coldchain!D162:D1160 = D162), purchase_order_lines_coldchain!B$2:B$1000, _xlfn.XLOOKUP(F162,purchase_order_lines_coldchain!A$2:A1160, purchase_order_lines_coldchain!B$2:B1160)), "")} | I162: =G162 & H162 -> PO000090 | J162: LOT-036-000161 | K162: 198 | L162: 198 | M162: 12.22 | N162: 2419.56 | O162: -0.7 | P162: Supplier_Delivery
A163: MOV0000162 | B163: 45702.159 | C163: Receipt | D163: WH-IBA-01 | E163: PRD00121 | F163: POL000255 | G163: PO000090 | H163: {=IF(AND(G163="", C163="Receipt"), _xlfn.XLOOKUP(1, (purchase_order_lines_coldchain!A163:A1161 = F163) * (purchase_order_lines_coldchain!G163:G1161 = E163) * (purchase_order_lines_coldchain!D163:D1161 = D163), purchase_order_lines_coldchain!B$2:B$1000, _xlfn.XLOOKUP(F163,purchase_order_lines_coldchain!A$2:A1161, purchase_order_lines_coldchain!B$2:B1161)), "")} | I163: =G163 & H163 -> PO000090 | J163: LOT-121-000162 | K163: 38 | L163: 38 | M163: 10.44 | N163: 396.72 | O163: 6.2 | P163: Supplier_Delivery
... A167: MOV0000166 | B167: 45723.097 | C167: Receipt | D167: WH-KAD-01 | E167: PRD00017 | F167: POL000089 | G167: PO000032 | H167: {=IF(AND(G167="", C167="Receipt"), _xlfn.XLOOKUP(1, (purchase_order_lines_coldchain!A167:A1165 = F167) * (purchase_order_lines_coldchain!G167:G1165 = E167) * (purchase_order_lines_coldchain!D167:D1165 = D167), purchase_order_lines_coldchain!B$2:B$1000, _xlfn.XLOOKUP(F167,purchase_order_lines_coldchain!A$2:A1165, purchase_order_lines_coldchain!B$2:B1165)), "")} | I167: =G167 & H167 -> PO000032 | J167: LOT-017-000166 | K167: 23 | L167: 23 | M167: 11.52 | N167: 264.96 | O167: 2.1 | P167: Supplier_Delivery
A168: MOV0000167 | B168: 45724.483 | C168: Receipt | D168: WH-BEN-01 | E168: PRD00165 | F168: POL000086 | H168: {=IF(AND(G168="", C168="Receipt"), _xlfn.XLOOKUP(1, (purchase_order_lines_coldchain!A168:A1166 = F168) * (purchase_order_lines_coldchain!G168:G1166 = E168) * (purchase_order_lines_coldchain!D168:D1166 = D168), purchase_order_lines_coldchain!B$2:B$1000, _xlfn.XLOOKUP(F168,purchase_order_lines_coldchain!A$2:A1166, purchase_order_lines_coldchain!B$2:B1166)), "")} -> PO000031 | I168: =G168 & H168 -> PO000031 | J168: LOT-165-000167 | K168: 86 | L168: 86 | M168: 15.17 | N168: 1304.62 | O168: 1.1 | P168: Supplier_Delivery
A169: MOV0000168 | B169: 45700.63 | C169: Receipt | D169: WH-ENU-01 | E169: PRD00051 | F169: POL000344 | G169: PO000123 | H169: {=IF(AND(G169="", C169="Receipt"), _xlfn.XLOOKUP(1, (purchase_order_lines_coldchain!A169:A1167 = F169) * (purchase_order_lines_coldchain!G169:G1167 = E169) * (purchase_order_lines_coldchain!D169:D1167 = D169), purchase_order_lines_coldchain!B$2:B$1000, _xlfn.XLOOKUP(F169,purchase_order_lines_coldchain!A$2:A1167, purchase_order_lines_coldchain!B$2:B1167)), "")} | I169: =G169 & H169 -> PO000123 | J169: LOT-051-000168 | K169: 119 | L169: 119 | M169: 1.65 | N169: 196.35 | O169: 2.2 | P169: Supplier_Delivery
A170: MOV0000169 | B170: 45679.796 | C170: Receipt | D170: WH-BEN-01 | E170: PRD00157 | F170: POL000175 | G170: PO000063 | H170: {=IF(AND(G170="", C170="Receipt"), _xlfn.XLOOKUP(1, (purchase_order_lines_coldchain!A170:A1168 = F170) * (purchase_order_lines_coldchain!G170:G1168 = E170) * (purchase_order_lines_coldchain!D170:D1168 = D170), purchase_order_lines_coldchain!B$2:B$1000, _xlfn.XLOOKUP(F170,purchase_order_lines_coldchain!A$2:A1168, purchase_order_lines_coldchain!B$2:B1168)), "")} | I170: =G170 & H170 -> PO000063 | J170: LOT-157-000169 | K170: 31 | L170: 31 | M170: 6.08 | N170: 188.48 | O170: 3.4 | P170: Supplier_Delivery
A171: MOV0000170 | B171: 45731.642 | C171: Receipt | D171: WH-KAD-01 | E171: PRD00002 | F171: POL000076 | G171: PO000027 | H171: {=IF(AND(G171="", C171="Receipt"), _xlfn.XLOOKUP(1, (purchase_order_lines_coldchain!A171:A1169 = F171) * (purchase_order_lines_coldchain!G171:G1169 = E171) * (purchase_order_lines_coldchain!D171:D1169 = D171), purchase_order_lines_coldchain!B$2:B$1000, _xlfn.XLOOKUP(F171,purchase_order_lines_coldchain!A$2:A1169, purchase_order_lines_coldchain!B$2:B1169)), "")} | I171: =G171 & H171 -> PO000027 | J171: LOT-002-000170 | K171: 161 | L171: 161 | M171: 5.92 | N171: 953.12 | O171: 5.8 | P171: Supplier_Delivery
A172: MOV0000171 | B172: 45703.13 | C172: Receipt | D172: WH-PHC-01 | E172: PRD00050 | F172: POL000111 | G172: PO000040 | H172: {=IF(AND(G172="", C172="Receipt"), _xlfn.XLOOKUP(1, (purchase_order_lines_coldchain!A172:A1170 = F172) * (purchase_order_lines_coldchain!G172:G1170 = E172) * (purchase_order_lines_coldchain!D172:D1170 = D172), purchase_order_lines_coldchain!B$2:B$1000, _xlfn.XLOOKUP(F172,purchase_order_lines_coldchain!A$2:A1170, purchase_order_lines_coldchain!B$2:B1170)), "")} | I172: =G172 & H172 -> PO000040 | J172: LOT-050-000171 | K172: 9 | L172: 9 | M172: 17.4 | N172: 156.6 | O172: 1.4 | P172: Supplier_Delivery
A173: MOV0000172 | B173: 45719.754 | C173: Receipt | D173: WH-PHC-01 | E173: PRD00138 | F173: POL000302 | G173: PO000107 | H173: {=IF(AND(G173="", C173="Receipt"), _xlfn.XLOOKUP(1, (purchase_order_lines_coldchain!A173:A1171 = F173) * (purchase_order_lines_coldchain!G173:G1171 = E173) * (purchase_order_lines_coldchain!D173:D1171 = D173), purchase_order_lines_coldchain!B$2:B$1000, _xlfn.XLOOKUP(F173,purchase_order_lines_coldchain!A$2:A1171, purchase_order_lines_coldchain!B$2:B1171)), "")} | I173: =G173 & H173 -> PO000107 | J173: LOT-138-000172 | K173: 71 | L173: 71 | M173: 9.82 | N173: 697.22 | O173: 2.9 | P173: Supplier_Delivery
A174: MOV0000173 | B174: 45746.863 | C174: Receipt | D174: WH-PHC-01 | E174: PRD00016 | F174: POL000207 | G174: PO000074 | H174: {=IF(AND(G174="", C174="Receipt"), _xlfn.XLOOKUP(1, (purchase_order_lines_coldchain!A174:A1172 = F174) * (purchase_order_lines_coldchain!G174:G1172 = E174) * (purchase_order_lines_coldchain!D174:D1172 = D174), purchase_order_lines_coldchain!B$2:B$1000, _xlfn.XLOOKUP(F174,purchase_order_lines_coldchain!A$2:A1172, purchase_order_lines_coldchain!B$2:B1172)), "")} | I174: =G174 & H174 -> PO000074 | J174: LOT-016-000173 | K174: 111 | L174: 111 | M174: 15.82 | N174: 1756.02 | O174: 6.2 | P174: Supplier_Delivery
A175: MOV0000174 | B175: 45707.187 | C175: Receipt | D175: WH-ABJ-01 | E175: PRD00032 | F175: POL000306 | G175: PO000109 | H175: {=IF(AND(G175="", C175="Receipt"), _xlfn.XLOOKUP(1, (purchase_order_lines_coldchain!A175:A1173 = F175) * (purchase_order_lines_coldchain!G175:G1173 = E175) * (purchase_order_lines_coldchain!D175:D1173 = D175), purchase_order_lines_coldchain!B$2:B$1000, _xlfn.XLOOKUP(F175,purchase_order_lines_coldchain!A$2:A1173, purchase_order_lines_coldchain!B$2:B1173)), "")} | I175: =G175 & H175 -> PO000109 | J175: LOT-032-000174 | K175: 100 | L175: 100 | M175: 2.38 | N175: 238 | O175: 4.7 | P175: Supplier_Delivery
A176: MOV0000175 | B176: 45708.485 | C176: Receipt | D176: WH-KAD-01 | E176: PRD00073 | F176: POL000410 | G176: PO000147 | H176: {=IF(AND(G176="", C176="Receipt"), _xlfn.XLOOKUP(1, (purchase_order_lines_coldchain!A176:A1174 = F176) * (purchase_order_lines_coldchain!G176:G1174 = E176) * (purchase_order_lines_coldchain!D176:D1174 = D176), purchase_order_lines_coldchain!B$2:B$1000, _xlfn.XLOOKUP(F176,purchase_order_lines_coldchain!A$2:A1174, purchase_order_lines_coldchain!B$2:B1174)), "")} | I176: =G176 & H176 -> PO000147 | J176: LOT-073-000175 | K176: 161 | L176: 161 | M176: 3.56 | N176: 573.16 | O176: 7.7 | P176: Supplier_Delivery
A177: MOV0000176 | B177: 45733.694 | C177: Receipt | D177: WH-LAG-02 | E177: PRD00075 | F177: POL000114 | G177: PO000041 | H177: {=IF(AND(G177="", C177="Receipt"), _xlfn.XLOOKUP(1, (purchase_order_lines_coldchain!A177:A1175 = F177) * (purchase_order_lines_coldchain!G177:G1175 = E177) * (purchase_order_lines_coldchain!D177:D1175 = D177), purchase_order_lines_coldchain!B$2:B$1000, _xlfn.XLOOKUP(F177,purchase_order_lines_coldchain!A$2:A1175, purchase_order_lines_coldchain!B$2:B1175)), "")} | I177: =G177 & H177 -> PO000041 | J177: LOT-075-000176 | K177: 136 | L177: 136 | M177: 11.84 | N177: 1610.24 | O177: 6.8 | P177: Supplier_Delivery
A178: MOV0000177 | B178: 45677.091 | C178: Receipt | D178: WH-IBA-01 | E178: PRD00100 | F178: POL000120 | G178: PO000044 | H178: {=IF(AND(G178="", C178="Receipt"), _xlfn.XLOOKUP(1, (purchase_order_lines_coldchain!A178:A1176 = F178) * (purchase_order_lines_coldchain!G178:G1176 = E178) * (purchase_order_lines_coldchain!D178:D1176 = D178), purchase_order_lines_coldchain!B$2:B$1000, _xlfn.XLOOKUP(F178,purchase_order_lines_coldchain!A$2:A1176, purchase_order_lines_coldchain!B$2:B1176)), "")} | I178: =G178 & H178 -> PO000044 | J178: LOT-100-000177 | K178: 92 | L178: 92 | M178: 12.33 | N178: 1134.36 | O178: 3.1 | P178: Supplier_Delivery
A179: MOV0000178 | B179: 45682.297 | C179: Receipt | D179: WH-LAG-01 | E179: PRD00092 | F179: POL000024 | G179: PO000009 | H179: {=IF(AND(G179="", C179="Receipt"), _xlfn.XLOOKUP(1, (purchase_order_lines_coldchain!A179:A1177 = F179) * (purchase_order_lines_coldchain!G179:G1177 = E179) * (purchase_order_lines_coldchain!D179:D1177 = D179), purchase_order_lines_coldchain!B$2:B$1000, _xlfn.XLOOKUP(F179,purchase_order_lines_coldchain!A$2:A1177, purchase_order_lines_coldchain!B$2:B1177)), "")} | I179: =G179 & H179 -> PO000009 | J179: LOT-092-000178 | K179: 155 | L179: 155 | M179: 4.36 | N179: 675.8 | O179: 5.8 | P179: Supplier_Delivery
A180: MOV0000179 | B180: 45739.766 | C180: Receipt | D180: WH-BEN-01 | E180: PRD00098 | F180: POL000050 | G180: PO000018 | H180: {=IF(AND(G180="", C180="Receipt"), _xlfn.XLOOKUP(1, (purchase_order_lines_coldchain!A180:A1178 = F180) * (purchase_order_lines_coldchain!G180:G1178 = E180) * (purchase_order_lines_coldchain!D180:D1178 = D180), purchase_order_lines_coldchain!B$2:B$1000, _xlfn.XLOOKUP(F180,purchase_order_lines_coldchain!A$2:A1178, purchase_order_lines_coldchain!B$2:B1178)), "")} | I180: =G180 & H180 -> PO000018 | J180: LOT-098-000179 | K180: 124 | L180: 124 | M180: 1.76 | N180: 218.24 | O180: 5.8 | P180: Supplier_Delivery
A181: MOV0000180 | B181: 45728.299 | C181: Receipt | D181: WH-LAG-01 | E181: PRD00161 | F181: POL000396 | H181: {=IF(AND(G181="", C181="Receipt"), _xlfn.XLOOKUP(1, (purchase_order_lines_coldchain!A181:A1179 = F181) * (purchase_order_lines_coldchain!G181:G1179 = E181) * (purchase_order_lines_coldchain!D181:D1179 = D181), purchase_order_lines_coldchain!B$2:B$1000, _xlfn.XLOOKUP(F181,purchase_order_lines_coldchain!A$2:A1179, purchase_order_lines_coldchain!B$2:B1179)), "")} -> PO000077 | I181: =G181 & H181 -> PO000077 | J181: LOT-161-000180 | K181: 175 | L181: 175 | M181: 3.81 | N181: 666.75 | O181: 1.6 | P181: Supplier_Delivery
A182: MOV0000181 | B182: 45715.383 | C182: Receipt | D182: WH-LAG-02 | E182: PRD00061 | F182: POL000061 | G182: PO000022 | H182: {=IF(AND(G182="", C182="Receipt"), _xlfn.XLOOKUP(1, (purchase_order_lines_coldchain!A182:A1180 = F182) * (purchase_order_lines_coldchain!G182:G1180 = E182) * (purchase_order_lines_coldchain!D182:D1180 = D182), purchase_order_lines_coldchain!B$2:B$1000, _xlfn.XLOOKUP(F182,purchase_order_lines_coldchain!A$2:A1180, purchase_order_lines_coldchain!B$2:B1180)), "")} | I182: =G182 & H182 -> PO000022 | J182: LOT-061-000181 | K182: 192 | L182: 192 | M182: 2.58 | N182: 495.36 | O182: 2.6 | P182: Supplier_Delivery
A183: MOV0000182 | B183: 45720.509 | C183: Receipt | D183: WH-IBA-01 | E183: PRD00161 | F183: POL000129 | G183: PO000047 | H183: {=IF(AND(G183="", C183="Receipt"), _xlfn.XLOOKUP(1, (purchase_order_lines_coldchain!A183:A1181 = F183) * (purchase_order_lines_coldchain!G183:G1181 = E183) * (purchase_order_lines_coldchain!D183:D1181 = D183), purchase_order_lines_coldchain!B$2:B$1000, _xlfn.XLOOKUP(F183,purchase_order_lines_coldchain!A$2:A1181, purchase_order_lines_coldchain!B$2:B1181)), "")} | I183: =G183 & H183 -> PO000047 | J183: LOT-161-000182 | K183: 66 | L183: 66 | M183: 3.51 | N183: 231.66 | O183: 4.3 | P183: Supplier_Delivery
A184: MOV0000183 | B184: 45734.526 | C184: Receipt | D184: WH-IBA-01 | E184: PRD00147 | F184: POL000145 | G184: PO000052 | H184: {=IF(AND(G184="", C184="Receipt"), _xlfn.XLOOKUP(1, (purchase_order_lines_coldchain!A184:A1182 = F184) * (purchase_order_lines_coldchain!G184:G1182 = E184) * (purchase_order_lines_coldchain!D184:D1182 = D184), purchase_order_lines_coldchain!B$2:B$1000, _xlfn.XLOOKUP(F184,purchase_order_lines_coldchain!A$2:A1182, purchase_order_lines_coldchain!B$2:B1182)), "")} | I184: =G184 & H184 -> PO000052 | J184: LOT-147-000183 | K184: 195 | L184: 195 | M184: 16.17 | N184: 3153.15 | O184: 7.3 | P184: Supplier_Delivery
A185: MOV0000184 | B185: 45686.122 | C185: Receipt | D185: WH-PHC-01 | E185: PRD00119 | F185: POL000293 | G185: PO000104 | H185: {=IF(AND(G185="", C185="Receipt"), _xlfn.XLOOKUP(1, (purchase_order_lines_coldchain!A185:A1183 = F185) * (purchase_order_lines_coldchain!G185:G1183 = E185) * (purchase_order_lines_coldchain!D185:D1183 = D185), purchase_order_lines_coldchain!B$2:B$1000, _xlfn.XLOOKUP(F185,purchase_order_lines_coldchain!A$2:A1183, purchase_order_lines_coldchain!B$2:B1183)), "")} | I185: =G185 & H185 -> PO000104 | J185: LOT-119-000184 | K185: 23 | L185: 23 | M185: 8.47 | N185: 194.81 | O185: 5.8 | P185: Supplier_Delivery
A186: MOV0000185 | B186: 45692.267 | C186: Receipt | D186: WH-LAG-01 | E186: PRD00122 | F186: POL000270 | G186: PO000096 | H186: {=IF(AND(G186="", C186="Receipt"), _xlfn.XLOOKUP(1, (purchase_order_lines_coldchain!A186:A1184 = F186) * (purchase_order_lines_coldchain!G186:G1184 = E186) * (purchase_order_lines_coldchain!D186:D1184 = D186), purchase_order_lines_coldchain!B$2:B$1000, _xlfn.XLOOKUP(F186,purchase_order_lines_coldchain!A$2:A1184, purchase_order_lines_coldchain!B$2:B1184)), "")} | I186: =G186 & H186 -> PO000096 | J186: LOT-122-000185 | K186: 93 | L186: 93 | M186: 4.03 | N186: 374.79 | O186: 3.8 | P186: Supplier_Delivery
A187: MOV0000186 | B187: 45706.156 | C187: Receipt | D187: WH-LAG-02 | E187: PRD00136 | F187: POL000125 | G187: PO000045 | H187: {=IF(AND(G187="", C187="Receipt"), _xlfn.XLOOKUP(1, (purchase_order_lines_coldchain!A187:A1185 = F187) * (purchase_order_lines_coldchain!G187:G1185 = E187) * (purchase_order_lines_coldchain!D187:D1185 = D187), purchase_order_lines_coldchain!B$2:B$1000, _xlfn.XLOOKUP(F187,purchase_order_lines_coldchain!A$2:A1185, purchase_order_lines_coldchain!B$2:B1185)), "")} | I187: =G187 & H187 -> PO000045 | J187: LOT-136-000186 | K187: 58 | L187: 58 | M187: 5.91 | N187: 342.78 | O187: 1.1 | P187: Supplier_Delivery
A188: MOV0000187 | B188: 45732.633 | C188: Receipt | D188: WH-ABJ-01 | E188: PRD00169 | F188: POL000019 | G188: PO000007 | H188: {=IF(AND(G188="", C188="Receipt"), _xlfn.XLOOKUP(1, (purchase_order_lines_coldchain!A188:A1186 = F188) * (purchase_order_lines_coldchain!G188:G1186 = E188) * (purchase_order_lines_coldchain!D188:D1186 = D188), purchase_order_lines_coldchain!B$2:B$1000, _xlfn.XLOOKUP(F188,purchase_order_lines_coldchain!A$2:A1186, purchase_order_lines_coldchain!B$2:B1186)), "")} | I188: =G188 & H188 -> PO000007 | J188: LOT-169-000187 | K188: 54 | L188: 54 | M188: 12.1 | N188: 653.4 | O188: 3.7 | P188: Supplier_Delivery
A189: MOV0000188 | B189: 45733.924 | C189: Receipt | D189: WH-ABJ-01 | E189: PRD00053 | F189: POL000017 | G189: PO000007 | H189: {=IF(AND(G189="", C189="Receipt"), _xlfn.XLOOKUP(1, (purchase_order_lines_coldchain!A189:A1187 = F189) * (purchase_order_lines_coldchain!G189:G1187 = E189) * (purchase_order_lines_coldchain!D189:D1187 = D189), purchase_order_lines_coldchain!B$2:B$1000, _xlfn.XLOOKUP(F189,purchase_order_lines_coldchain!A$2:A1187, purchase_order_lines_coldchain!B$2:B1187)), "")} | I189: =G189 & H189 -> PO000007 | J189: LOT-053-000188 | K189: 194 | L189: 194 | M189: 12.86 | N189: 2494.84 | O189: 6.1 | P189: Supplier_Delivery
A190: MOV0000189 | B190: 45669.591 | C190: Receipt | D190: WH-IBA-01 | E190: PRD00064 | F190: POL000336 | G190: PO000119 | H190: {=IF(AND(G190="", C190="Receipt"), _xlfn.XLOOKUP(1, (purchase_order_lines_coldchain!A190:A1188 = F190) * (purchase_order_lines_coldchain!G190:G1188 = E190) * (purchase_order_lines_coldchain!D190:D1188 = D190), purchase_order_lines_coldchain!B$2:B$1000, _xlfn.XLOOKUP(F190,purchase_order_lines_coldchain!A$2:A1188, purchase_order_lines_coldchain!B$2:B1188)), "")} | I190: =G190 & H190 -> PO000119 | J190: LOT-064-000189 | K190: 119 | L190: 119 | M190: 2.84 | N190: 337.96 | O190: 3.6 | P190: Supplier_Delivery
A191: MOV0000190 | B191: 45732.392 | C191: Receipt | D191: WH-PHC-01 | E191: PRD00066 | F191: POL000137 | G191: PO000050 | H191: {=IF(AND(G191="", C191="Receipt"), _xlfn.XLOOKUP(1, (purchase_order_lines_coldchain!A191:A1189 = F191) * (purchase_order_lines_coldchain!G191:G1189 = E191) * (purchase_order_lines_coldchain!D191:D1189 = D191), purchase_order_lines_coldchain!B$2:B$1000, _xlfn.XLOOKUP(F191,purchase_order_lines_coldchain!A$2:A1189, purchase_order_lines_coldchain!B$2:B1189)), "")} | I191: =G191 & H191 -> PO000050 | J191: LOT-066-000190 | K191: 46 | L191: 46 | M191: 4.69 | N191: 215.74 | O191: 7.5 | P191: Supplier_Delivery
A192: MOV0000191 | B192: 45668.09 | C192: Receipt | D192: WH-AWK-01 | E192: PRD00066 | F192: POL000393 | G192: PO000141 | H192: {=IF(AND(G192="", C192="Receipt"), _xlfn.XLOOKUP(1, (purchase_order_lines_coldchain!A192:A1190 = F192) * (purchase_order_lines_coldchain!G192:G1190 = E192) * (purchase_order_lines_coldchain!D192:D1190 = D192), purchase_order_lines_coldchain!B$2:B$1000, _xlfn.XLOOKUP(F192,purchase_order_lines_coldchain!A$2:A1190, purchase_order_lines_coldchain!B$2:B1190)), "")} | I192: =G192 & H192 -> PO000141 | J192: LOT-066-000191 | K192: 120 | L192: 120 | M192: 4.6 | N192: 552 | O192: 6.4 | P192: Supplier_Delivery
A193: MOV0000192 | B193: 45691.006 | C193: Receipt | D193: WH-BEN-01 | E193: PRD00064 | F193: POL000419 | G193: PO000150 | H193: {=IF(AND(G193="", C193="Receipt"), _xlfn.XLOOKUP(1, (purchase_order_lines_coldchain!A193:A1191 = F193) * (purchase_order_lines_coldchain!G193:G1191 = E193) * (purchase_order_lines_coldchain!D193:D1191 = D193), purchase_order_lines_coldchain!B$2:B$1000, _xlfn.XLOOKUP(F193,purchase_order_lines_coldchain!A$2:A1191, purchase_order_lines_coldchain!B$2:B1191)), "")} | I193: =G193 & H193 -> PO000150 | J193: LOT-064-000192 | K193: 184 | L193: 184 | M193: 2.9 | N193: 533.6 | O193: 3.8 | P193: Supplier_Delivery
... A321: MOV0000320 | B321: 45722.433 | C321: Receipt | D321: WH-IBA-01 | E321: PRD00157 | F321: POL000060 | G321: PO000021 | H321: {=IF(AND(G321="", C321="Receipt"), _xlfn.XLOOKUP(1, (purchase_order_lines_coldchain!A321:A1319 = F321) * (purchase_order_lines_coldchain!G321:G1319 = E321) * (purchase_order_lines_coldchain!D321:D1319 = D321), purchase_order_lines_coldchain!B$2:B$1000, _xlfn.XLOOKUP(F321,purchase_order_lines_coldchain!A$2:A1319, purchase_order_lines_coldchain!B$2:B1319)), "")} | I321: =G321 & H321 -> PO000021 | J321: LOT-157-000320 | K321: 40 | L321: 40 | M321: 6.22 | N321: 248.8 | O321: 0.5 | P321: Supplier_Delivery
A322: MOV0000321 | B322: 45723.678 | C322: Dispatch | D322: WH-ENU-01 | E322: PRD00176 | G322: SO-189088 | H322: {=IF(AND(G322="", C322="Receipt"), _xlfn.XLOOKUP(1, (purchase_order_lines_coldchain!A322:A1320 = F322) * (purchase_order_lines_coldchain!G322:G1320 = E322) * (purchase_order_lines_coldchain!D322:D1320 = D322), purchase_order_lines_coldchain!B$2:B$1000, _xlfn.XLOOKUP(F322,purchase_order_lines_coldchain!A$2:A1320, purchase_order_lines_coldchain!B$2:B1320)), "")} | I322: =G322 & H322 -> SO-189088 | K322: 5 | L322: -5 | M322: 4.86 | N322: -24.3 | O322: -0.4 | P322: Customer_Order_Fulfillment
A323: MOV0000322 | B323: 45722.857 | C323: Dispatch | D323: WH-PHC-01 | E323: PRD00151 | G323: SO-145145 | H323: {=IF(AND(G323="", C323="Receipt"), _xlfn.XLOOKUP(1, (purchase_order_lines_coldchain!A323:A1321 = F323) * (purchase_order_lines_coldchain!G323:G1321 = E323) * (purchase_order_lines_coldchain!D323:D1321 = D323), purchase_order_lines_coldchain!B$2:B$1000, _xlfn.XLOOKUP(F323,purchase_order_lines_coldchain!A$2:A1321, purchase_order_lines_coldchain!B$2:B1321)), "")} | I323: =G323 & H323 -> SO-145145 | K323: 11 | L323: -11 | M323: 5.99 | N323: -65.89 | O323: -0.2 | P323: Customer_Order_Fulfillment
A324: MOV0000323 | B324: 45763.784 | C324: Sale | D324: WH-KAD-01 | E324: PRD00125 | G324: SO-186113 | H324: {=IF(AND(G324="", C324="Receipt"), _xlfn.XLOOKUP(1, (purchase_order_lines_coldchain!A324:A1322 = F324) * (purchase_order_lines_coldchain!G324:G1322 = E324) * (purchase_order_lines_coldchain!D324:D1322 = D324), purchase_order_lines_coldchain!B$2:B$1000, _xlfn.XLOOKUP(F324,purchase_order_lines_coldchain!A$2:A1322, purchase_order_lines_coldchain!B$2:B1322)), "")} | I324: =G324 & H324 -> SO-186113 | K324: 7 | L324: -7 | M324: 15.68 | N324: -109.76 | O324: -15.8 | P324: Customer_Order_Fulfillment
A325: MOV0000324 | B325: 45754.745 | C325: Sale | D325: WH-LAG-01 | E325: PRD00070 | G325: SO-197896 | H325: {=IF(AND(G325="", C325="Receipt"), _xlfn.XLOOKUP(1, (purchase_order_lines_coldchain!A325:A1323 = F325) * (purchase_order_lines_coldchain!G325:G1323 = E325) * (purchase_order_lines_coldchain!D325:D1323 = D325), purchase_order_lines_coldchain!B$2:B$1000, _xlfn.XLOOKUP(F325,purchase_order_lines_coldchain!A$2:A1323, purchase_order_lines_coldchain!B$2:B1323)), "")} | I325: =G325 & H325 -> SO-197896 | K325: 4 | L325: -4 | M325: 6.21 | N325: -24.84 | O325: -0.3 | P325: Customer_Order_Fulfillment
A326: MOV0000325 | B326: 45759.776 | C326: Sale | D326: WH-JOS-01 | E326: PRD00168 | G326: SO-121892 | H326: {=IF(AND(G326="", C326="Receipt"), _xlfn.XLOOKUP(1, (purchase_order_lines_coldchain!A326:A1324 = F326) * (purchase_order_lines_coldchain!G326:G1324 = E326) * (purchase_order_lines_coldchain!D326:D1324 = D326), purchase_order_lines_coldchain!B$2:B$1000, _xlfn.XLOOKUP(F326,purchase_order_lines_coldchain!A$2:A1324, purchase_order_lines_coldchain!B$2:B1324)), "")} | I326: =G326 & H326 -> SO-121892 | K326: 7 | L326: -7 | M326: 15.97 | N326: -111.79 | O326: 4.3 | P326: Customer_Order_Fulfillment
A327: MOV0000326 | B327: 45757.517 | C327: Sale | D327: WH-IBA-01 | E327: PRD00118 | G327: SO-158368 | H327: {=IF(AND(G327="", C327="Receipt"), _xlfn.XLOOKUP(1, (purchase_order_lines_coldchain!A327:A1325 = F327) * (purchase_order_lines_coldchain!G327:G1325 = E327) * (purchase_order_lines_coldchain!D327:D1325 = D327), purchase_order_lines_coldchain!B$2:B$1000, _xlfn.XLOOKUP(F327,purchase_order_lines_coldchain!A$2:A1325, purchase_order_lines_coldchain!B$2:B1325)), "")} | I327: =G327 & H327 -> SO-158368 | K327: 12 | L327: -12 | M327: 11.21 | N327: -134.52 | O327: 7 | P327: Customer_Order_Fulfillment
A328: MOV0000327 | B328: 45749.915 | C328: Sale | D328: WH-AWK-01 | E328: PRD00178 | G328: SO-172509 | H328: {=IF(AND(G328="", C328="Receipt"), _xlfn.XLOOKUP(1, (purchase_order_lines_coldchain!A328:A1326 = F328) * (purchase_order_lines_coldchain!G328:G1326 = E328) * (purchase_order_lines_coldchain!D328:D1326 = D328), purchase_order_lines_coldchain!B$2:B$1000, _xlfn.XLOOKUP(F328,purchase_order_lines_coldchain!A$2:A1326, purchase_order_lines_coldchain!B$2:B1326)), "")} | I328: =G328 & H328 -> SO-172509 | K328: 9 | L328: -9 | M328: 4.25 | N328: -38.25 | O328: 0.5 | P328: Customer_Order_Fulfillment
A329: MOV0000328 | B329: 45753.306 | C329: Sale | D329: WH-BEN-01 | E329: PRD00090 | G329: SO-109493 | H329: {=IF(AND(G329="", C329="Receipt"), _xlfn.XLOOKUP(1, (purchase_order_lines_coldchain!A329:A1327 = F329) * (purchase_order_lines_coldchain!G329:G1327 = E329) * (purchase_order_lines_coldchain!D329:D1327 = D329), purchase_order_lines_coldchain!B$2:B$1000, _xlfn.XLOOKUP(F329,purchase_order_lines_coldchain!A$2:A1327, purchase_order_lines_coldchain!B$2:B1327)), "")} | I329: =G329 & H329 -> SO-109493 | K329: 1 | L329: -1 | M329: 6.57 | N329: -6.57 | O329: 0.1 | P329: Customer_Order_Fulfillment
A330: MOV0000329 | B330: 45760.285 | C330: Dispatch | D330: WH-BEN-01 | E330: PRD00146 | G330: SO-106213 | H330: {=IF(AND(G330="", C330="Receipt"), _xlfn.XLOOKUP(1, (purchase_order_lines_coldchain!A330:A1328 = F330) * (purchase_order_lines_coldchain!G330:G1328 = E330) * (purchase_order_lines_coldchain!D330:D1328 = D330), purchase_order_lines_coldchain!B$2:B$1000, _xlfn.XLOOKUP(F330,purchase_order_lines_coldchain!A$2:A1328, purchase_order_lines_coldchain!B$2:B1328)), "")} | I330: =G330 & H330 -> SO-106213 | K330: 7 | L330: -7 | M330: 8.13 | N330: -56.91 | O330: 5.4 | P330: Customer_Order_Fulfillment
A331: MOV0000330 | B331: 45760.306 | C331: Sale | D331: WH-IBA-01 | E331: PRD00036 | G331: SO-107203 | H331: {=IF(AND(G331="", C331="Receipt"), _xlfn.XLOOKUP(1, (purchase_order_lines_coldchain!A331:A1329 = F331) * (purchase_order_lines_coldchain!G331:G1329 = E331) * (purchase_order_lines_coldchain!D331:D1329 = D331), purchase_order_lines_coldchain!B$2:B$1000, _xlfn.XLOOKUP(F331,purchase_order_lines_coldchain!A$2:A1329, purchase_order_lines_coldchain!B$2:B1329)), "")} | I331: =G331 & H331 -> SO-107203 | K331: 4 | L331: -4 | M331: 12.97 | N331: -51.88 | O331: 1.2 | P331: Customer_Order_Fulfillment
A332: MOV0000331 | B332: 45761.435 | C332: Sale | D332: WH-IBA-01 | E332: PRD00161 | G332: SO-113619 | H332: {=IF(AND(G332="", C332="Receipt"), _xlfn.XLOOKUP(1, (purchase_order_lines_coldchain!A332:A1330 = F332) * (purchase_order_lines_coldchain!G332:G1330 = E332) * (purchase_order_lines_coldchain!D332:D1330 = D332), purchase_order_lines_coldchain!B$2:B$1000, _xlfn.XLOOKUP(F332,purchase_order_lines_coldchain!A$2:A1330, purchase_order_lines_coldchain!B$2:B1330)), "")} | I332: =G332 & H332 -> SO-113619 | K332: 12 | L332: -12 | M332: 3.81 | N332: -45.72 | O332: 4.9 | P332: Customer_Order_Fulfillment
A333: MOV0000332 | B333: 45748.807 | C333: Sale | D333: WH-AWK-01 | E333: PRD00150 | G333: SO-151694 | H333: {=IF(AND(G333="", C333="Receipt"), _xlfn.XLOOKUP(1, (purchase_order_lines_coldchain!A333:A1331 = F333) * (purchase_order_lines_coldchain!G333:G1331 = E333) * (purchase_order_lines_coldchain!D333:D1331 = D333), purchase_order_lines_coldchain!B$2:B$1000, _xlfn.XLOOKUP(F333,purchase_order_lines_coldchain!A$2:A1331, purchase_order_lines_coldchain!B$2:B1331)), "")} | I333: =G333 & H333 -> SO-151694 | K333: 8 | L333: -8 | M333: 13.7 | N333: -109.6 | O333: 2.8 | P333: Customer_Order_Fulfillment
... A373: MOV0000372 | B373: 45742.713 | C373: Sale | D373: WH-KAD-01 | E373: PRD00045 | G373: SO-164253 | H373: {=IF(AND(G373="", C373="Receipt"), _xlfn.XLOOKUP(1, (purchase_order_lines_coldchain!A373:A1371 = F373) * (purchase_order_lines_coldchain!G373:G1371 = E373) * (purchase_order_lines_coldchain!D373:D1371 = D373), purchase_order_lines_coldchain!B$2:B$1000, _xlfn.XLOOKUP(F373,purchase_order_lines_coldchain!A$2:A1371, purchase_order_lines_coldchain!B$2:B1371)), "")} | I373: =G373 & H373 -> SO-164253 | K373: 2 | L373: -2 | M373: 6.71 | N373: -13.42 | O373: 8.1 | P373: Customer_Order_Fulfillment
A374: MOV0000373 | B374: 45739.25 | C374: Dispatch | D374: WH-ENU-01 | E374: PRD00071 | H374: {=IF(AND(G374="", C374="Receipt"), _xlfn.XLOOKUP(1, (purchase_order_lines_coldchain!A374:A1372 = F374) * (purchase_order_lines_coldchain!G374:G1372 = E374) * (purchase_order_lines_coldchain!D374:D1372 = D374), purchase_order_lines_coldchain!B$2:B$1000, _xlfn.XLOOKUP(F374,purchase_order_lines_coldchain!A$2:A1372, purchase_order_lines_coldchain!B$2:B1372)), "")} | I374: =G374 & H374 | K374: 2 | L374: -2 | M374: 10.01 | N374: -20.02 | O374: 1.1 | P374: Customer_Order_Fulfillment
A375: MOV0000374 | B375: 45765.711 | C375: Dispatch | D375: WH-BEN-01 | E375: PRD00017 | G375: SO-119810 | H375: {=IF(AND(G375="", C375="Receipt"), _xlfn.XLOOKUP(1, (purchase_order_lines_coldchain!A375:A1373 = F375) * (purchase_order_lines_coldchain!G375:G1373 = E375) * (purchase_order_lines_coldchain!D375:D1373 = D375), purchase_order_lines_coldchain!B$2:B$1000, _xlfn.XLOOKUP(F375,purchase_order_lines_coldchain!A$2:A1373, purchase_order_lines_coldchain!B$2:B1373)), "")} | I375: =G375 & H375 -> SO-119810 | K375: 10 | L375: -10 | M375: 12.39 | N375: -123.9 | O375: 2 | P375: Customer_Order_Fulfillment
A376: MOV0000375 | B376: 45756.659 | C376: Dispatch | D376: WH-IBA-01 | E376: PRD00151 | G376: SO-184075 | H376: {=IF(AND(G376="", C376="Receipt"), _xlfn.XLOOKUP(1, (purchase_order_lines_coldchain!A376:A1374 = F376) * (purchase_order_lines_coldchain!G376:G1374 = E376) * (purchase_order_lines_coldchain!D376:D1374 = D376), purchase_order_lines_coldchain!B$2:B$1000, _xlfn.XLOOKUP(F376,purchase_order_lines_coldchain!A$2:A1374, purchase_order_lines_coldchain!B$2:B1374)), "")} | I376: =G376 & H376 -> SO-184075 | K376: 4 | L376: -4 | M376: 5.99 | N376: -23.96 | O376: -2.9 | P376: Customer_Order_Fulfillment
A377: MOV0000376 | B377: 45707.159 | C377: Sale | D377: WH-KAD-01 | E377: PRD00113 | G377: SO-117147 | H377: {=IF(AND(G377="", C377="Receipt"), _xlfn.XLOOKUP(1, (purchase_order_lines_coldchain!A377:A1375 = F377) * (purchase_order_lines_coldchain!G377:G1375 = E377) * (purchase_order_lines_coldchain!D377:D1375 = D377), purchase_order_lines_coldchain!B$2:B$1000, _xlfn.XLOOKUP(F377,purchase_order_lines_coldchain!A$2:A1375, purchase_order_lines_coldchain!B$2:B1375)), "")} | I377: =G377 & H377 -> SO-117147 | K377: 9 | L377: -9 | M377: 5.39 | N377: -48.51 | O377: 7 | P377: Customer_Order_Fulfillment
A378: MOV0000377 | B378: 45722.433 | C378: Sale | D378: WH-ABJ-01 | E378: PRD00101 | G378: SO-105559 | H378: {=IF(AND(G378="", C378="Receipt"), _xlfn.XLOOKUP(1, (purchase_order_lines_coldchain!A378:A1376 = F378) * (purchase_order_lines_coldchain!G378:G1376 = E378) * (purchase_order_lines_coldchain!D378:D1376 = D378), purchase_order_lines_coldchain!B$2:B$1000, _xlfn.XLOOKUP(F378,purchase_order_lines_coldchain!A$2:A1376, purchase_order_lines_coldchain!B$2:B1376)), "")} | I378: =G378 & H378 -> SO-105559 | K378: 12 | L378: -12 | M378: 10.13 | N378: -121.56 | O378: 3.2 | P378: Customer_Order_Fulfillment
A379: MOV0000378 | B379: 45710.974 | C379: Sale | D379: WH-ENU-01 | E379: PRD00051 | G379: SO-154992 | H379: {=IF(AND(G379="", C379="Receipt"), _xlfn.XLOOKUP(1, (purchase_order_lines_coldchain!A379:A1377 = F379) * (purchase_order_lines_coldchain!G379:G1377 = E379) * (purchase_order_lines_coldchain!D379:D1377 = D379), purchase_order_lines_coldchain!B$2:B$1000, _xlfn.XLOOKUP(F379,purchase_order_lines_coldchain!A$2:A1377, purchase_order_lines_coldchain!B$2:B1377)), "")} | I379: =G379 & H379 -> SO-154992 | K379: 11 | L379: -11 | M379: 1.77 | N379: -19.47 | O379: 4.9 | P379: Customer_Order_Fulfillment
A380: MOV0000379 | B380: 45777.078 | C380: Dispatch | D380: WH-ENU-01 | E380: PRD00037 | G380: SO-151002 | H380: {=IF(AND(G380="", C380="Receipt"), _xlfn.XLOOKUP(1, (purchase_order_lines_coldchain!A380:A1378 = F380) * (purchase_order_lines_coldchain!G380:G1378 = E380) * (purchase_order_lines_coldchain!D380:D1378 = D380), purchase_order_lines_coldchain!B$2:B$1000, _xlfn.XLOOKUP(F380,purchase_order_lines_coldchain!A$2:A1378, purchase_order_lines_coldchain!B$2:B1378)), "")} | I380: =G380 & H380 -> SO-151002 | K380: 10 | L380: -10 | M380: 12.48 | N380: -124.8 | O380: 6.7 | P380: Customer_Order_Fulfillment
A381: MOV0000380 | B381: 45736.873 | C381: Sale | D381: WH-ABJ-01 | E381: PRD00146 | G381: SO-184531 | H381: {=IF(AND(G381="", C381="Receipt"), _xlfn.XLOOKUP(1, (purchase_order_lines_coldchain!A381:A1379 = F381) * (purchase_order_lines_coldchain!G381:G1379 = E381) * (purchase_order_lines_coldchain!D381:D1379 = D381), purchase_order_lines_coldchain!B$2:B$1000, _xlfn.XLOOKUP(F381,purchase_order_lines_coldchain!A$2:A1379, purchase_order_lines_coldchain!B$2:B1379)), "")} | I381: =G381 & H381 -> SO-184531 | K381: 10 | L381: -10 | M381: 8.13 | N381: -81.3 | O381: 1 | P381: Customer_Order_Fulfillment
A382: MOV0000381 | B382: 45703.136 | C382: Sale | D382: WH-ABJ-01 | E382: PRD00135 | G382: SO-180174 | H382: {=IF(AND(G382="", C382="Receipt"), _xlfn.XLOOKUP(1, (purchase_order_lines_coldchain!A382:A1380 = F382) * (purchase_order_lines_coldchain!G382:G1380 = E382) * (purchase_order_lines_coldchain!D382:D1380 = D382), purchase_order_lines_coldchain!B$2:B$1000, _xlfn.XLOOKUP(F382,purchase_order_lines_coldchain!A$2:A1380, purchase_order_lines_coldchain!B$2:B1380)), "")} | I382: =G382 & H382 -> SO-180174 | K382: 12 | L382: -12 | M382: 11.96 | N382: -143.52 | O382: -2.1 | P382: Customer_Order_Fulfillment
A383: MOV0000382 | B383: 45744.228 | C383: Dispatch | D383: WH-AWK-01 | E383: PRD00122 | G383: SO-130547 | H383: {=IF(AND(G383="", C383="Receipt"), _xlfn.XLOOKUP(1, (purchase_order_lines_coldchain!A383:A1381 = F383) * (purchase_order_lines_coldchain!G383:G1381 = E383) * (purchase_order_lines_coldchain!D383:D1381 = D383), purchase_order_lines_coldchain!B$2:B$1000, _xlfn.XLOOKUP(F383,purchase_order_lines_coldchain!A$2:A1381, purchase_order_lines_coldchain!B$2:B1381)), "")} | I383: =G383 & H383 -> SO-130547 | K383: 8 | L383: -8 | M383: 3.82 | N383: -30.56 | O383: 4.1 | P383: Customer_Order_Fulfillment
A384: MOV0000383 | B384: 45771.724 | C384: Sale | D384: WH-PHC-01 | E384: PRD00050 | G384: SO-120513 | H384: {=IF(AND(G384="", C384="Receipt"), _xlfn.XLOOKUP(1, (purchase_order_lines_coldchain!A384:A1382 = F384) * (purchase_order_lines_coldchain!G384:G1382 = E384) * (purchase_order_lines_coldchain!D384:D1382 = D384), purchase_order_lines_coldchain!B$2:B$1000, _xlfn.XLOOKUP(F384,purchase_order_lines_coldchain!A$2:A1382, purchase_order_lines_coldchain!B$2:B1382)), "")} | I384: =G384 & H384 -> SO-120513 | K384: 8 | L384: -8 | M384: 16.69 | N384: -133.52 | O384: 4.2 | P384: Customer_Order_Fulfillment
A385: MOV0000384 | B385: 45722.543 | C385: Dispatch | D385: WH-ENU-01 | E385: PRD00004 | G385: SO-169910 | H385: {=IF(AND(G385="", C385="Receipt"), _xlfn.XLOOKUP(1, (purchase_order_lines_coldchain!A385:A1383 = F385) * (purchase_order_lines_coldchain!G385:G1383 = E385) * (purchase_order_lines_coldchain!D385:D1383 = D385), purchase_order_lines_coldchain!B$2:B$1000, _xlfn.XLOOKUP(F385,purchase_order_lines_coldchain!A$2:A1383, purchase_order_lines_coldchain!B$2:B1383)), "")} | I385: =G385 & H385 -> SO-169910 | K385: 5 | L385: -5 | M385: 4.96 | N385: -24.8 | O385: 4 | P385: Customer_Order_Fulfillment
A386: MOV0000385 | B386: 45729.491 | C386: Dispatch | D386: WH-BEN-01 | E386: PRD00064 | G386: SO-197416 | H386: {=IF(AND(G386="", C386="Receipt"), _xlfn.XLOOKUP(1, (purchase_order_lines_coldchain!A386:A1384 = F386) * (purchase_order_lines_coldchain!G386:G1384 = E386) * (purchase_order_lines_coldchain!D386:D1384 = D386), purchase_order_lines_coldchain!B$2:B$1000, _xlfn.XLOOKUP(F386,purchase_order_lines_coldchain!A$2:A1384, purchase_order_lines_coldchain!B$2:B1384)), "")} | I386: =G386 & H386 -> SO-197416 | K386: 6 | L386: -6 | M386: 2.84 | N386: -17.04 | O386: 4.4 | P386: Customer_Order_Fulfillment
... A420: MOV0000419 | B420: 45704.751 | C420: Sale | D420: WH-LAG-01 | E420: PRD00161 | G420: SO-170140 | H420: {=IF(AND(G420="", C420="Receipt"), _xlfn.XLOOKUP(1, (purchase_order_lines_coldchain!A420:A1418 = F420) * (purchase_order_lines_coldchain!G420:G1418 = E420) * (purchase_order_lines_coldchain!D420:D1418 = D420), purchase_order_lines_coldchain!B$2:B$1000, _xlfn.XLOOKUP(F420,purchase_order_lines_coldchain!A$2:A1418, purchase_order_lines_coldchain!B$2:B1418)), "")} | I420: =G420 & H420 -> SO-170140 | K420: 10 | L420: -10 | M420: 3.81 | N420: -38.1 | O420: 5 | P420: Customer_Order_Fulfillment
A421: MOV0000420 | B421: 45725.412 | C421: Dispatch | D421: WH-ABJ-01 | E421: PRD00042 | H421: {=IF(AND(G421="", C421="Receipt"), _xlfn.XLOOKUP(1, (purchase_order_lines_coldchain!A421:A1419 = F421) * (purchase_order_lines_coldchain!G421:G1419 = E421) * (purchase_order_lines_coldchain!D421:D1419 = D421), purchase_order_lines_coldchain!B$2:B$1000, _xlfn.XLOOKUP(F421,purchase_order_lines_coldchain!A$2:A1419, purchase_order_lines_coldchain!B$2:B1419)), "")} | I421: =G421 & H421 | K421: 7 | L421: -7 | M421: 13.86 | N421: -97.02 | O421: 5.1 | P421: Customer_Order_Fulfillment
A422: MOV0000421 | B422: 45717.819 | C422: Sale | D422: WH-JOS-01 | E422: PRD00006 | G422: SO-117734 | H422: {=IF(AND(G422="", C422="Receipt"), _xlfn.XLOOKUP(1, (purchase_order_lines_coldchain!A422:A1420 = F422) * (purchase_order_lines_coldchain!G422:G1420 = E422) * (purchase_order_lines_coldchain!D422:D1420 = D422), purchase_order_lines_coldchain!B$2:B$1000, _xlfn.XLOOKUP(F422,purchase_order_lines_coldchain!A$2:A1420, purchase_order_lines_coldchain!B$2:B1420)), "")} | I422: =G422 & H422 -> SO-117734 | K422: 10 | L422: -10 | M422: 8.14 | N422: -81.4 | O422: 2 | P422: Customer_Order_Fulfillment
A423: MOV0000422 | B423: 45745.787 | C423: Sale | D423: WH-IBA-01 | E423: PRD00006 | G423: SO-193919 | H423: {=IF(AND(G423="", C423="Receipt"), _xlfn.XLOOKUP(1, (purchase_order_lines_coldchain!A423:A1421 = F423) * (purchase_order_lines_coldchain!G423:G1421 = E423) * (purchase_order_lines_coldchain!D423:D1421 = D423), purchase_order_lines_coldchain!B$2:B$1000, _xlfn.XLOOKUP(F423,purchase_order_lines_coldchain!A$2:A1421, purchase_order_lines_coldchain!B$2:B1421)), "")} | I423: =G423 & H423 -> SO-193919 | K423: 7 | L423: -7 | M423: 8.14 | N423: -56.98 | O423: 6.3 | P423: Customer_Order_Fulfillment
A424: MOV0000423 | B424: 45743.43 | C424: Sale | D424: WH-ABJ-01 | E424: PRD00161 | G424: SO-197525 | H424: {=IF(AND(G424="", C424="Receipt"), _xlfn.XLOOKUP(1, (purchase_order_lines_coldchain!A424:A1422 = F424) * (purchase_order_lines_coldchain!G424:G1422 = E424) * (purchase_order_lines_coldchain!D424:D1422 = D424), purchase_order_lines_coldchain!B$2:B$1000, _xlfn.XLOOKUP(F424,purchase_order_lines_coldchain!A$2:A1422, purchase_order_lines_coldchain!B$2:B1422)), "")} | I424: =G424 & H424 -> SO-197525 | K424: 8 | L424: -8 | M424: 3.81 | N424: -30.48 | O424: 4.5 | P424: Customer_Order_Fulfillment
...

Sheet cycle_counts_coldchain
A1: count_id | B1: warehouse_id | C1: product_id | D1: count_date | E1: system_qty | F1: system_qty_Check | G1: counted_qty | H1: variance | I1: variance_check | J1: count_type | K1: counted_by | L1: notes
A2: CC000001 | B2: WH-LAG-02 | C2: PRD00043 | D2: 45774.433 | E2: 0 | F2: =IF(E2=(SUMIFS(stock_movements_coldchain[signed_qty],stock_movements_coldchain[product_id],C2,stock_movements_coldchain[warehouse_id],B2,stock_movements_coldchain[movement_date],"<" &'cycle_counts_coldchain'!D2)),"Pass","Investigate") -> Pass | G2: 0 | H2: 0 | I2: =IF((G2-E2)=H2,"Pass","Investigate") -> Pass | J2: Full | K2: I. Musa | L2: Cold Room Audit
A3: CC000002 | B3: WH-LAG-02 | C3: PRD00039 | D3: 45757.54 | E3: 0 | F3: =IF(E3=(SUMIFS(stock_movements_coldchain[signed_qty],stock_movements_coldchain[product_id],C3,stock_movements_coldchain[warehouse_id],B3,stock_movements_coldchain[movement_date],"<" &'cycle_counts_coldchain'!D3)),"Pass","Investigate") -> Pass | G3: 0 | H3: 0 | I3: =IF((G3-E3)=H3,"Pass","Investigate") -> Pass | J3: Spot | K3: I. Musa | L3: Near Expiry Review
A4: CC000003 | B4: WH-IBA-01 | C4: PRD00048 | D4: 45749.373 | E4: 0 | F4: =IF(E4=(SUMIFS(stock_movements_coldchain[signed_qty],stock_movements_coldchain[product_id],C4,stock_movements_coldchain[warehouse_id],B4,stock_movements_coldchain[movement_date],"<" &'cycle_counts_coldchain'!D4)),"Pass","Investigate") -> Pass | G4: 4 | H4: 4 | I4: =IF((G4-E4)=H4,"Pass","Investigate") -> Pass | J4: Cycle | K4: A. Ibrahim
A5: CC000004 | B5: WH-JOS-01 | C5: PRD00017 | D5: 45774.117 | E5: 0 | F5: =IF(E5=(SUMIFS(stock_movements_coldchain[signed_qty],stock_movements_coldchain[product_id],C5,stock_movements_coldchain[warehouse_id],B5,stock_movements_coldchain[movement_date],"<" &'cycle_counts_coldchain'!D5)),"Pass","Investigate") -> Pass | G5: 0 | H5: 0 | I5: =IF((G5-E5)=H5,"Pass","Investigate") -> Pass | J5: Cycle | K5: F. Adebayo | L5: Cold Room Audit
A6: CC000005 | B6: WH-BEN-01 | C6: PRD00124 | D6: 45689.584 | E6: 0 | F6: =IF(E6=(SUMIFS(stock_movements_coldchain[signed_qty],stock_movements_coldchain[product_id],C6,stock_movements_coldchain[warehouse_id],B6,stock_movements_coldchain[movement_date],"<" &'cycle_counts_coldchain'!D6)),"Pass","Investigate") -> Pass | G6: 0 | H6: 0 | I6: =IF((G6-E6)=H6,"Pass","Investigate") -> Pass | J6: Cycle | K6: I. Musa | L6: Fefo Check
A7: CC000006 | B7: WH-LAG-01 | C7: PRD00092 | D7: 45760.557 | E7: 740 | F7: =IF(E7=(SUMIFS(stock_movements_coldchain[signed_qty],stock_movements_coldchain[product_id],C7,stock_movements_coldchain[warehouse_id],B7,stock_movements_coldchain[movement_date],"<" &'cycle_counts_coldchain'!D7)),"Pass","Investigate") -> Pass | G7: 737 | H7: -3 | I7: =IF((G7-E7)=H7,"Pass","Investigate") -> Pass | J7: Cycle | K7: S. Bello | L7: Cold Room Audit
A8: CC000007 | B8: WH-PHC-01 | C8: PRD00022 | D8: 45678.001 | E8: 0 | F8: =IF(E8=(SUMIFS(stock_movements_coldchain[signed_qty],stock_movements_coldchain[product_id],C8,stock_movements_coldchain[warehouse_id],B8,stock_movements_coldchain[movement_date],"<" &'cycle_counts_coldchain'!D8)),"Pass","Investigate") -> Pass | G8: 3 | H8: 3 | I8: =IF((G8-E8)=H8,"Pass","Investigate") -> Pass | J8: Cycle | K8: I. Musa | L8: Fefo Check
A9: CC000008 | B9: WH-KAD-01 | C9: PRD00062 | D9: 45746.144 | E9: 0 | F9: =IF(E9=(SUMIFS(stock_movements_coldchain[signed_qty],stock_movements_coldchain[product_id],C9,stock_movements_coldchain[warehouse_id],B9,stock_movements_coldchain[movement_date],"<" &'cycle_counts_coldchain'!D9)),"Pass","Investigate") -> Pass | G9: 0 | H9: 0 | I9: =IF((G9-E9)=H9,"Pass","Investigate") -> Pass | J9: Spot | K9: A. Ibrahim
A10: CC000009 | B10: WH-ENU-01 | C10: PRD00138 | D10: 45776.608 | E10: 0 | F10: =IF(E10=(SUMIFS(stock_movements_coldchain[signed_qty],stock_movements_coldchain[product_id],C10,stock_movements_coldchain[warehouse_id],B10,stock_movements_coldchain[movement_date],"<" &'cycle_counts_coldchain'!D10)),"Pass","Investigate") -> Pass | G10: 0 | H10: 0 | I10: =IF((G10-E10)=H10,"Pass","Investigate") -> Pass | J10: Cycle | K10: F. Adebayo | L10: Fefo Check
A11: CC000010 | B11: WH-IBA-01 | C11: PRD00063 | D11: 45743.109 | E11: 0 | F11: =IF(E11=(SUMIFS(stock_movements_coldchain[signed_qty],stock_movements_coldchain[product_id],C11,stock_movements_coldchain[warehouse_id],B11,stock_movements_coldchain[movement_date],"<" &'cycle_counts_coldchain'!D11)),"Pass","Investigate") -> Pass | G11: 0 | H11: 0 | I11: =IF((G11-E11)=H11,"Pass","Investigate") -> Pass | J11: Spot | K11: S. Bello
A12: CC000011 | B12: WH-IBA-01 | C12: PRD00113 | D12: 45725.146 | E12: 0 | F12: =IF(E12=(SUMIFS(stock_movements_coldchain[signed_qty],stock_movements_coldchain[product_id],C12,stock_movements_coldchain[warehouse_id],B12,stock_movements_coldchain[movement_date],"<" &'cycle_counts_coldchain'!D12)),"Pass","Investigate") -> Pass | G12: 2 | H12: 2 | I12: =IF((G12-E12)=H12,"Pass","Investigate") -> Pass | J12: Cycle | K12: S. Bello
A13: CC000012 | B13: WH-KAD-01 | C13: PRD00046 | D13: 45701.228 | E13: 0 | F13: =IF(E13=(SUMIFS(stock_movements_coldchain[signed_qty],stock_movements_coldchain[product_id],C13,stock_movements_coldchain[warehouse_id],B13,stock_movements_coldchain[movement_date],"<" &'cycle_counts_coldchain'!D13)),"Pass","Investigate") -> Pass | G13: 0 | H13: 0 | I13: =IF((G13-E13)=H13,"Pass","Investigate") -> Pass | J13: Full | K13: A. Ibrahim
A14: CC000013 | B14: WH-PHC-01 | C14: PRD00150 | D14: 45707.963 | E14: 0 | F14: =IF(E14=(SUMIFS(stock_movements_coldchain[signed_qty],stock_movements_coldchain[product_id],C14,stock_movements_coldchain[warehouse_id],B14,stock_movements_coldchain[movement_date],"<" &'cycle_counts_coldchain'!D14)),"Pass","Investigate") -> Pass | G14: 0 | H14: 0 | I14: =IF((G14-E14)=H14,"Pass","Investigate") -> Pass | J14: Full | K14: S. Bello | L14: Near Expiry Review
A15: CC000014 | B15: WH-JOS-01 | C15: PRD00049 | D15: 45682.876 | E15: 0 | F15: =IF(E15=(SUMIFS(stock_movements_coldchain[signed_qty],stock_movements_coldchain[product_id],C15,stock_movements_coldchain[warehouse_id],B15,stock_movements_coldchain[movement_date],"<" &'cycle_counts_coldchain'!D15)),"Pass","Investigate") -> Pass | G15: 0 | H15: 0 | I15: =IF((G15-E15)=H15,"Pass","Investigate") -> Pass | J15: Cycle | K15: F. Adebayo | L15: Fefo Check
A16: CC000015 | B16: WH-KAD-01 | C16: PRD00048 | D16: 45682.701 | E16: 0 | F16: =IF(E16=(SUMIFS(stock_movements_coldchain[signed_qty],stock_movements_coldchain[product_id],C16,stock_movements_coldchain[warehouse_id],B16,stock_movements_coldchain[movement_date],"<" &'cycle_counts_coldchain'!D16)),"Pass","Investigate") -> Pass | G16: 0 | H16: 0 | I16: =IF((G16-E16)=H16,"Pass","Investigate") -> Pass | J16: Cycle | K16: A. Ibrahim | L16: Near Expiry Review
A17: CC000016 | B17: WH-AWK-01 | C17: PRD00060 | D17: 45678.722 | E17: 0 | F17: =IF(E17=(SUMIFS(stock_movements_coldchain[signed_qty],stock_movements_coldchain[product_id],C17,stock_movements_coldchain[warehouse_id],B17,stock_movements_coldchain[movement_date],"<" &'cycle_counts_coldchain'!D17)),"Pass","Investigate") -> Pass | G17: 0 | H17: 0 | I17: =IF((G17-E17)=H17,"Pass","Investigate") -> Pass | J17: Spot | K17: I. Musa | L17: Near Expiry Review
A18: CC000017 | B18: WH-IBA-01 | C18: PRD00011 | D18: 45769.399 | E18: 0 | F18: =IF(E18=(SUMIFS(stock_movements_coldchain[signed_qty],stock_movements_coldchain[product_id],C18,stock_movements_coldchain[warehouse_id],B18,stock_movements_coldchain[movement_date],"<" &'cycle_counts_coldchain'!D18)),"Pass","Investigate") -> Pass | G18: 3 | H18: 3 | I18: =IF((G18-E18)=H18,"Pass","Investigate") -> Pass | J18: Cycle | K18: S. Bello | L18: Fefo Check
A19: CC000018 | B19: WH-IBA-01 | C19: PRD00169 | D19: 45718.39 | E19: 0 | F19: =IF(E19=(SUMIFS(stock_movements_coldchain[signed_qty],stock_movements_coldchain[product_id],C19,stock_movements_coldchain[warehouse_id],B19,stock_movements_coldchain[movement_date],"<" &'cycle_counts_coldchain'!D19)),"Pass","Investigate") -> Pass | G19: 0 | H19: 0 | I19: =IF((G19-E19)=H19,"Pass","Investigate") -> Pass | J19: Full | K19: S. Bello | L19: Cold Room Audit
A20: CC000019 | B20: WH-PHC-01 | C20: PRD00097 | D20: 45742.142 | E20: 0 | F20: =IF(E20=(SUMIFS(stock_movements_coldchain[signed_qty],stock_movements_coldchain[product_id],C20,stock_movements_coldchain[warehouse_id],B20,stock_movements_coldchain[movement_date],"<" &'cycle_counts_coldchain'!D20)),"Pass","Investigate") -> Pass | G20: 3 | H20: 3 | I20: =IF((G20-E20)=H20,"Pass","Investigate") -> Pass | J20: Spot | K20: S. Bello | L20: Fefo Check
A21: CC000020 | B21: WH-BEN-01 | C21: PRD00048 | D21: 45739.583 | E21: 0 | F21: =IF(E21=(SUMIFS(stock_movements_coldchain[signed_qty],stock_movements_coldchain[product_id],C21,stock_movements_coldchain[warehouse_id],B21,stock_movements_coldchain[movement_date],"<" &'cycle_counts_coldchain'!D21)),"Pass","Investigate") -> Pass | G21: 0 | H21: 0 | I21: =IF((G21-E21)=H21,"Pass","Investigate") -> Pass | J21: Full | K21: A. Ibrahim | L21: Near Expiry Review
A22: CC000021 | B22: WH-ENU-01 | C22: PRD00022 | D22: 45699.422 | E22: 0 | F22: =IF(E22=(SUMIFS(stock_movements_coldchain[signed_qty],stock_movements_coldchain[product_id],C22,stock_movements_coldchain[warehouse_id],B22,stock_movements_coldchain[movement_date],"<" &'cycle_counts_coldchain'!D22)),"Pass","Investigate") -> Pass | G22: 0 | H22: 0 | I22: =IF((G22-E22)=H22,"Pass","Investigate") -> Pass | J22: Cycle | K22: F. Adebayo
A23: CC000022 | B23: WH-PHC-01 | C23: PRD00056 | D23: 45689.245 | E23: 0 | F23: =IF(E23=(SUMIFS(stock_movements_coldchain[signed_qty],stock_movements_coldchain[product_id],C23,stock_movements_coldchain[warehouse_id],B23,stock_movements_coldchain[movement_date],"<" &'cycle_counts_coldchain'!D23)),"Pass","Investigate") -> Pass | G23: 4 | H23: 4 | I23: =IF((G23-E23)=H23,"Pass","Investigate") -> Pass | J23: Cycle | K23: S. Bello | L23: Near Expiry Review
A24: CC000023 | B24: WH-ENU-01 | C24: PRD00168 | D24: 45682.426 | E24: 0 | F24: =IF(E24=(SUMIFS(stock_movements_coldchain[signed_qty],stock_movements_coldchain[product_id],C24,stock_movements_coldchain[warehouse_id],B24,stock_movements_coldchain[movement_date],"<" &'cycle_counts_coldchain'!D24)),"Pass","Investigate") -> Pass | G24: 0 | H24: 0 | I24: =IF((G24-E24)=H24,"Pass","Investigate") -> Pass | J24: Full | K24: F. Adebayo
A25: CC000024 | B25: WH-LAG-02 | C25: PRD00134 | D25: 45770.458 | E25: 0 | F25: =IF(E25=(SUMIFS(stock_movements_coldchain[signed_qty],stock_movements_coldchain[product_id],C25,stock_movements_coldchain[warehouse_id],B25,stock_movements_coldchain[movement_date],"<" &'cycle_counts_coldchain'!D25)),"Pass","Investigate") -> Pass | G25: 4 | H25: 4 | I25: =IF((G25-E25)=H25,"Pass","Investigate") -> Pass | J25: Spot | K25: I. Musa
A26: CC000025 | B26: WH-LAG-02 | C26: PRD00158 | D26: 45686.351 | E26: 0 | F26: =IF(E26=(SUMIFS(stock_movements_coldchain[signed_qty],stock_movements_coldchain[product_id],C26,stock_movements_coldchain[warehouse_id],B26,stock_movements_coldchain[movement_date],"<" &'cycle_counts_coldchain'!D26)),"Pass","Investigate") -> Pass | G26: 4 | H26: 4 | I26: =IF((G26-E26)=H26,"Pass","Investigate") -> Pass | J26: Full | K26: F. Adebayo | L26: Near Expiry Review
A27: CC000026 | B27: WH-LAG-02 | C27: PRD00035 | D27: 45698.628 | E27: 0 | F27: =IF(E27=(SUMIFS(stock_movements_coldchain[signed_qty],stock_movements_coldchain[product_id],C27,stock_movements_coldchain[warehouse_id],B27,stock_movements_coldchain[movement_date],"<" &'cycle_counts_coldchain'!D27)),"Pass","Investigate") -> Pass | G27: 0 | H27: 0 | I27: =IF((G27-E27)=H27,"Pass","Investigate") -> Pass | J27: Spot | K27: I. Musa | L27: Fefo Check
A28: CC000027 | B28: WH-BEN-01 | C28: PRD00171 | D28: 45773.512 | E28: 75 | F28: =IF(E28=(SUMIFS(stock_movements_coldchain[signed_qty],stock_movements_coldchain[product_id],C28,stock_movements_coldchain[warehouse_id],B28,stock_movements_coldchain[movement_date],"<" &'cycle_counts_coldchain'!D28)),"Pass","Investigate") -> Pass | G28: 78 | H28: 3 | I28: =IF((G28-E28)=H28,"Pass","Investigate") -> Pass | J28: Cycle | K28: F. Adebayo
A29: CC000028 | B29: WH-JOS-01 | C29: PRD00065 | D29: 45731.348 | E29: 0 | F29: =IF(E29=(SUMIFS(stock_movements_coldchain[signed_qty],stock_movements_coldchain[product_id],C29,stock_movements_coldchain[warehouse_id],B29,stock_movements_coldchain[movement_date],"<" &'cycle_counts_coldchain'!D29)),"Pass","Investigate") -> Pass | G29: 2 | H29: 2 | I29: =IF((G29-E29)=H29,"Pass","Investigate") -> Pass | J29: Full | K29: A. Ibrahim | L29: Fefo Check
A30: CC000029 | B30: WH-JOS-01 | C30: PRD00022 | D30: 45749.201 | E30: 0 | F30: =IF(E30=(SUMIFS(stock_movements_coldchain[signed_qty],stock_movements_coldchain[product_id],C30,stock_movements_coldchain[warehouse_id],B30,stock_movements_coldchain[movement_date],"<" &'cycle_counts_coldchain'!D30)),"Pass","Investigate") -> Pass | G30: 0 | H30: 0 | I30: =IF((G30-E30)=H30,"Pass","Investigate") -> Pass | J30: Cycle | K30: I. Musa | L30: Fefo Check
A31: CC000030 | B31: WH-LAG-02 | C31: PRD00031 | D31: 45752.887 | E31: 0 | F31: =IF(E31=(SUMIFS(stock_movements_coldchain[signed_qty],stock_movements_coldchain[product_id],C31,stock_movements_coldchain[warehouse_id],B31,stock_movements_coldchain[movement_date],"<" &'cycle_counts_coldchain'!D31)),"Pass","Investigate") -> Pass | G31: 3 | H31: 3 | I31: =IF((G31-E31)=H31,"Pass","Investigate") -> Pass | J31: Cycle | K31: I. Musa | L31: Cold Room Audit
A32: CC000031 | B32: WH-PHC-01 | C32: PRD00034 | D32: 45772.913 | E32: 0 | F32: =IF(E32=(SUMIFS(stock_movements_coldchain[signed_qty],stock_movements_coldchain[product_id],C32,stock_movements_coldchain[warehouse_id],B32,stock_movements_coldchain[movement_date],"<" &'cycle_counts_coldchain'!D32)),"Pass","Investigate") -> Pass | G32: 0 | H32: 0 | I32: =IF((G32-E32)=H32,"Pass","Investigate") -> Pass | J32: Full | K32: F. Adebayo | L32: Near Expiry Review
A33: CC000032 | B33: WH-LAG-01 | C33: PRD00074 | D33: 45749.214 | E33: 0 | F33: =IF(E33=(SUMIFS(stock_movements_coldchain[signed_qty],stock_movements_coldchain[product_id],C33,stock_movements_coldchain[warehouse_id],B33,stock_movements_coldchain[movement_date],"<" &'cycle_counts_coldchain'!D33)),"Pass","Investigate") -> Pass | G33: 0 | H33: 0 | I33: =IF((G33-E33)=H33,"Pass","Investigate") -> Pass | J33: Cycle | K33: F. Adebayo | L33: Cold Room Audit
A34: CC000033 | B34: WH-LAG-02 | C34: PRD00154 | D34: 45752.058 | E34: 0 | F34: =IF(E34=(SUMIFS(stock_movements_coldchain[signed_qty],stock_movements_coldchain[product_id],C34,stock_movements_coldchain[warehouse_id],B34,stock_movements_coldchain[movement_date],"<" &'cycle_counts_coldchain'!D34)),"Pass","Investigate") -> Pass | G34: 1 | H34: 1 | I34: =IF((G34-E34)=H34,"Pass","Investigate") -> Pass | J34: Spot | K34: S. Bello | L34: Cold Room Audit
A35: CC000034 | B35: WH-PHC-01 | C35: PRD00092 | D35: 45709.022 | E35: 0 | F35: =IF(E35=(SUMIFS(stock_movements_coldchain[signed_qty],stock_movements_coldchain[product_id],C35,stock_movements_coldchain[warehouse_id],B35,stock_movements_coldchain[movement_date],"<" &'cycle_counts_coldchain'!D35)),"Pass","Investigate") -> Pass | G35: 1 | H35: 1 | I35: =IF((G35-E35)=H35,"Pass","Investigate") -> Pass | J35: Cycle | K35: F. Adebayo | L35: Near Expiry Review
A36: CC000035 | B36: WH-BEN-01 | C36: PRD00123 | D36: 45718.224 | E36: 0 | F36: =IF(E36=(SUMIFS(stock_movements_coldchain[signed_qty],stock_movements_coldchain[product_id],C36,stock_movements_coldchain[warehouse_id],B36,stock_movements_coldchain[movement_date],"<" &'cycle_counts_coldchain'!D36)),"Pass","Investigate") -> Pass | G36: 0 | H36: 0 | I36: =IF((G36-E36)=H36,"Pass","Investigate") -> Pass | J36: Full | K36: A. Ibrahim | L36: Near Expiry Review
A37: CC000036 | B37: WH-PHC-01 | C37: PRD00104 | D37: 45695.482 | E37: 0 | F37: =IF(E37=(SUMIFS(stock_movements_coldchain[signed_qty],stock_movements_coldchain[product_id],C37,stock_movements_coldchain[warehouse_id],B37,stock_movements_coldchain[movement_date],"<" &'cycle_counts_coldchain'!D37)),"Pass","Investigate") -> Pass | G37: 0 | H37: 0 | I37: =IF((G37-E37)=H37,"Pass","Investigate") -> Pass | J37: Spot | K37: A. Ibrahim | L37: Cold Room Audit
A38: CC000037 | B38: WH-LAG-01 | C38: PRD00112 | D38: 45728.137 | E38: 0 | F38: =IF(E38=(SUMIFS(stock_movements_coldchain[signed_qty],stock_movements_coldchain[product_id],C38,stock_movements_coldchain[warehouse_id],B38,stock_movements_coldchain[movement_date],"<" &'cycle_counts_coldchain'!D38)),"Pass","Investigate") -> Pass | G38: 0 | H38: 0 | I38: =IF((G38-E38)=H38,"Pass","Investigate") -> Pass | J38: Cycle | K38: F. Adebayo | L38: Near Expiry Review
A39: CC000038 | B39: WH-AWK-01 | C39: PRD00100 | D39: 45706.201 | E39: 0 | F39: =IF(E39=(SUMIFS(stock_movements_coldchain[signed_qty],stock_movements_coldchain[product_id],C39,stock_movements_coldchain[warehouse_id],B39,stock_movements_coldchain[movement_date],"<" &'cycle_counts_coldchain'!D39)),"Pass","Investigate") -> Pass | G39: 4 | H39: 4 | I39: =IF((G39-E39)=H39,"Pass","Investigate") -> Pass | J39: Spot | K39: I. Musa
A40: CC000039 | B40: WH-IBA-01 | C40: PRD00037 | D40: 45694.438 | E40: 0 | F40: =IF(E40=(SUMIFS(stock_movements_coldchain[signed_qty],stock_movements_coldchain[product_id],C40,stock_movements_coldchain[warehouse_id],B40,stock_movements_coldchain[movement_date],"<" &'cycle_counts_coldchain'!D40)),"Pass","Investigate") -> Pass | G40: 1 | H40: 1 | I40: =IF((G40-E40)=H40,"Pass","Investigate") -> Pass | J40: Full | K40: F. Adebayo | L40: Cold Room Audit
A41: CC000040 | B41: WH-LAG-02 | C41: PRD00151 | D41: 45772.63 | E41: 6 | F41: =IF(E41=(SUMIFS(stock_movements_coldchain[signed_qty],stock_movements_coldchain[product_id],C41,stock_movements_coldchain[warehouse_id],B41,stock_movements_coldchain[movement_date],"<" &'cycle_counts_coldchain'!D41)),"Pass","Investigate") -> Pass | G41: 6 | H41: 0 | I41: =IF((G41-E41)=H41,"Pass","Investigate") -> Pass | J41: Cycle | K41: F. Adebayo | L41: Fefo Check
A42: CC000041 | B42: WH-ENU-01 | C42: PRD00091 | D42: 45736.72 | E42: 0 | F42: =IF(E42=(SUMIFS(stock_movements_coldchain[signed_qty],stock_movements_coldchain[product_id],C42,stock_movements_coldchain[warehouse_id],B42,stock_movements_coldchain[movement_date],"<" &'cycle_counts_coldchain'!D42)),"Pass","Investigate") -> Pass | G42: 3 | H42: 3 | I42: =IF((G42-E42)=H42,"Pass","Investigate") -> Pass | J42: Spot | K42: F. Adebayo
A43: CC000042 | B43: WH-JOS-01 | C43: PRD00038 | D43: 45723.581 | E43: 0 | F43: =IF(E43=(SUMIFS(stock_movements_coldchain[signed_qty],stock_movements_coldchain[product_id],C43,stock_movements_coldchain[warehouse_id],B43,stock_movements_coldchain[movement_date],"<" &'cycle_counts_coldchain'!D43)),"Pass","Investigate") -> Pass | G43: 0 | H43: 0 | I43: =IF((G43-E43)=H43,"Pass","Investigate") -> Pass | J43: Cycle | K43: I. Musa
A44: CC000043 | B44: WH-LAG-01 | C44: PRD00125 | D44: 45756.546 | E44: 0 | F44: =IF(E44=(SUMIFS(stock_movements_coldchain[signed_qty],stock_movements_coldchain[product_id],C44,stock_movements_coldchain[warehouse_id],B44,stock_movements_coldchain[movement_date],"<" &'cycle_counts_coldchain'!D44)),"Pass","Investigate") -> Pass | G44: 0 | H44: 0 | I44: =IF((G44-E44)=H44,"Pass","Investigate") -> Pass | J44: Spot | K44: A. Ibrahim | L44: Fefo Check
A45: CC000044 | B45: WH-BEN-01 | C45: PRD00110 | D45: 45751.394 | E45: 0 | F45: =IF(E45=(SUMIFS(stock_movements_coldchain[signed_qty],stock_movements_coldchain[product_id],C45,stock_movements_coldchain[warehouse_id],B45,stock_movements_coldchain[movement_date],"<" &'cycle_counts_coldchain'!D45)),"Pass","Investigate") -> Pass | G45: 1 | H45: 1 | I45: =IF((G45-E45)=H45,"Pass","Investigate") -> Pass | J45: Cycle | K45: I. Musa
A46: CC000045 | B46: WH-BEN-01 | C46: PRD00042 | D46: 45743.48 | E46: 7 | F46: =IF(E46=(SUMIFS(stock_movements_coldchain[signed_qty],stock_movements_coldchain[product_id],C46,stock_movements_coldchain[warehouse_id],B46,stock_movements_coldchain[movement_date],"<" &'cycle_counts_coldchain'!D46)),"Pass","Investigate") -> Pass | G46: 5 | H46: -2 | I46: =IF((G46-E46)=H46,"Pass","Investigate") -> Pass | J46: Full | K46: S. Bello | L46: Cold Room Audit
A47: CC000046 | B47: WH-ABJ-01 | C47: PRD00092 | D47: 45705.613 | E47: 0 | F47: =IF(E47=(SUMIFS(stock_movements_coldchain[signed_qty],stock_movements_coldchain[product_id],C47,stock_movements_coldchain[warehouse_id],B47,stock_movements_coldchain[movement_date],"<" &'cycle_counts_coldchain'!D47)),"Pass","Investigate") -> Pass | G47: 1 | H47: 1 | I47: =IF((G47-E47)=H47,"Pass","Investigate") -> Pass | J47: Spot | K47: S. Bello | L47: Near Expiry Review
A48: CC000047 | B48: WH-ENU-01 | C48: PRD00123 | D48: 45763.427 | E48: 0 | F48: =IF(E48=(SUMIFS(stock_movements_coldchain[signed_qty],stock_movements_coldchain[product_id],C48,stock_movements_coldchain[warehouse_id],B48,stock_movements_coldchain[movement_date],"<" &'cycle_counts_coldchain'!D48)),"Pass","Investigate") -> Pass | G48: 0 | H48: 0 | I48: =IF((G48-E48)=H48,"Pass","Investigate") -> Pass | J48: Cycle | K48: I. Musa | L48: Cold Room Audit
A49: CC000048 | B49: WH-LAG-02 | C49: PRD00056 | D49: 45736.158 | E49: 0 | F49: =IF(E49=(SUMIFS(stock_movements_coldchain[signed_qty],stock_movements_coldchain[product_id],C49,stock_movements_coldchain[warehouse_id],B49,stock_movements_coldchain[movement_date],"<" &'cycle_counts_coldchain'!D49)),"Pass","Investigate") -> Pass | G49: 3 | H49: 3 | I49: =IF((G49-E49)=H49,"Pass","Investigate") -> Pass | J49: Spot | K49: F. Adebayo | L49: Fefo Check
A50: CC000049 | B50: WH-ENU-01 | C50: PRD00084 | D50: 45736.769 | E50: 0 | F50: =IF(E50=(SUMIFS(stock_movements_coldchain[signed_qty],stock_movements_coldchain[product_id],C50,stock_movements_coldchain[warehouse_id],B50,stock_movements_coldchain[movement_date],"<" &'cycle_counts_coldchain'!D50)),"Pass","Investigate") -> Pass | G50: 0 | H50: 0 | I50: =IF((G50-E50)=H50,"Pass","Investigate") -> Pass | J50: Full | K50: A. Ibrahim
A51: CC000050 | B51: WH-BEN-01 | C51: PRD00067 | D51: 45743.494 | E51: 182 | F51: =IF(E51=(SUMIFS(stock_movements_coldchain[signed_qty],stock_movements_coldchain[product_id],C51,stock_movements_coldchain[warehouse_id],B51,stock_movements_coldchain[movement_date],"<" &'cycle_counts_coldchain'!D51)),"Pass","Investigate") -> Pass | G51: 178 | H51: -4 | I51: =IF((G51-E51)=H51,"Pass","Investigate") -> Pass | J51: Full | K51: F. Adebayo | L51: Cold Room Audit
A52: CC000051 | B52: WH-PHC-01 | C52: PRD00162 | D52: 45727.329 | E52: 0 | F52: =IF(E52=(SUMIFS(stock_movements_coldchain[signed_qty],stock_movements_coldchain[product_id],C52,stock_movements_coldchain[warehouse_id],B52,stock_movements_coldchain[movement_date],"<" &'cycle_counts_coldchain'!D52)),"Pass","Investigate") -> Pass | G52: 1 | H52: 1 | I52: =IF((G52-E52)=H52,"Pass","Investigate") -> Pass | J52: Spot | K52: I. Musa
A53: CC000052 | B53: WH-ABJ-01 | C53: PRD00057 | D53: 45714.545 | E53: 0 | F53: =IF(E53=(SUMIFS(stock_movements_coldchain[signed_qty],stock_movements_coldchain[product_id],C53,stock_movements_coldchain[warehouse_id],B53,stock_movements_coldchain[movement_date],"<" &'cycle_counts_coldchain'!D53)),"Pass","Investigate") -> Pass | G53: 4 | H53: 4 | I53: =IF((G53-E53)=H53,"Pass","Investigate") -> Pass | J53: Cycle | K53: F. Adebayo | L53: Cold Room Audit
A54: CC000053 | B54: WH-PHC-01 | C54: PRD00024 | D54: 45740.554 | E54: 0 | F54: =IF(E54=(SUMIFS(stock_movements_coldchain[signed_qty],stock_movements_coldchain[product_id],C54,stock_movements_coldchain[warehouse_id],B54,stock_movements_coldchain[movement_date],"<" &'cycle_counts_coldchain'!D54)),"Pass","Investigate") -> Pass | G54: 2 | H54: 2 | I54: =IF((G54-E54)=H54,"Pass","Investigate") -> Pass | J54: Cycle | K54: F. Adebayo | L54: Fefo Check
A55: CC000054 | B55: WH-IBA-01 | C55: PRD00082 | D55: 45698.84 | E55: 0 | F55: =IF(E55=(SUMIFS(stock_movements_coldchain[signed_qty],stock_movements_coldchain[product_id],C55,stock_movements_coldchain[warehouse_id],B55,stock_movements_coldchain[movement_date],"<" &'cycle_counts_coldchain'!D55)),"Pass","Investigate") -> Pass | G55: 0 | H55: 0 | I55: =IF((G55-E55)=H55,"Pass","Investigate") -> Pass | J55: Cycle | K55: F. Adebayo | L55: Fefo Check
A56: CC000055 | B56: WH-LAG-02 | C56: PRD00125 | D56: 45700.785 | E56: 0 | F56: =IF(E56=(SUMIFS(stock_movements_coldchain[signed_qty],stock_movements_coldchain[product_id],C56,stock_movements_coldchain[warehouse_id],B56,stock_movements_coldchain[movement_date],"<" &'cycle_counts_coldchain'!D56)),"Pass","Investigate") -> Pass | G56: 1 | H56: 1 | I56: =IF((G56-E56)=H56,"Pass","Investigate") -> Pass | J56: Spot | K56: S. Bello | L56: Near Expiry Review
A57: CC000056 | B57: WH-LAG-01 | C57: PRD00145 | D57: 45738.19 | E57: 0 | F57: =IF(E57=(SUMIFS(stock_movements_coldchain[signed_qty],stock_movements_coldchain[product_id],C57,stock_movements_coldchain[warehouse_id],B57,stock_movements_coldchain[movement_date],"<" &'cycle_counts_coldchain'!D57)),"Pass","Investigate") -> Pass | G57: 0 | H57: 0 | I57: =IF((G57-E57)=H57,"Pass","Investigate") -> Pass | J57: Cycle | K57: I. Musa | L57: Fefo Check
A58: CC000057 | B58: WH-ENU-01 | C58: PRD00101 | D58: 45732.943 | E58: 0 | F58: =IF(E58=(SUMIFS(stock_movements_coldchain[signed_qty],stock_movements_coldchain[product_id],C58,stock_movements_coldchain[warehouse_id],B58,stock_movements_coldchain[movement_date],"<" &'cycle_counts_coldchain'!D58)),"Pass","Investigate") -> Pass | G58: 3 | H58: 3 | I58: =IF((G58-E58)=H58,"Pass","Investigate") -> Pass | J58: Spot | K58: A. Ibrahim | L58: Near Expiry Review
A59: CC000058 | B59: WH-KAD-01 | C59: PRD00148 | D59: 45687.131 | E59: 0 | F59: =IF(E59=(SUMIFS(stock_movements_coldchain[signed_qty],stock_movements_coldchain[product_id],C59,stock_movements_coldchain[warehouse_id],B59,stock_movements_coldchain[movement_date],"<" &'cycle_counts_coldchain'!D59)),"Pass","Investigate") -> Pass | G59: 3 | H59: 3 | I59: =IF((G59-E59)=H59,"Pass","Investigate") -> Pass | J59: Full | K59: A. Ibrahim | L59: Fefo Check
A60: CC000059 | B60: WH-PHC-01 | C60: PRD00102 | D60: 45731.603 | E60: 60 | F60: =IF(E60=(SUMIFS(stock_movements_coldchain[signed_qty],stock_movements_coldchain[product_id],C60,stock_movements_coldchain[warehouse_id],B60,stock_movements_coldchain[movement_date],"<" &'cycle_counts_coldchain'!D60)),"Pass","Investigate") -> Pass | G60: 59 | H60: -1 | I60: =IF((G60-E60)=H60,"Pass","Investigate") -> Pass | J60: Cycle | K60: S. Bello | L60: Cold Room Audit
A61: CC000060 | B61: WH-KAD-01 | C61: PRD00159 | D61: 45744.32 | E61: 191 | F61: =IF(E61=(SUMIFS(stock_movements_coldchain[signed_qty],stock_movements_coldchain[product_id],C61,stock_movements_coldchain[warehouse_id],B61,stock_movements_coldchain[movement_date],"<" &'cycle_counts_coldchain'!D61)),"Pass","Investigate") -> Pass | G61: 191 | H61: 0 | I61: =IF((G61-E61)=H61,"Pass","Investigate") -> Pass | J61: Cycle | K61: F. Adebayo
A62: CC000061 | B62: WH-AWK-01 | C62: PRD00177 | D62: 45760.076 | E62: 0 | F62: =IF(E62=(SUMIFS(stock_movements_coldchain[signed_qty],stock_movements_coldchain[product_id],C62,stock_movements_coldchain[warehouse_id],B62,stock_movements_coldchain[movement_date],"<" &'cycle_counts_coldchain'!D62)),"Pass","Investigate") -> Pass | G62: 2 | H62: 2 | I62: =IF((G62-E62)=H62,"Pass","Investigate") -> Pass | J62: Cycle | K62: F. Adebayo | L62: Fefo Check
A63: CC000062 | B63: WH-IBA-01 | C63: PRD00029 | D63: 45732.719 | E63: 0 | F63: =IF(E63=(SUMIFS(stock_movements_coldchain[signed_qty],stock_movements_coldchain[product_id],C63,stock_movements_coldchain[warehouse_id],B63,stock_movements_coldchain[movement_date],"<" &'cycle_counts_coldchain'!D63)),"Pass","Investigate") -> Pass | G63: 0 | H63: 0 | I63: =IF((G63-E63)=H63,"Pass","Investigate") -> Pass | J63: Spot | K63: I. Musa | L63: Near Expiry Review
A64: CC000063 | B64: WH-BEN-01 | C64: PRD00097 | D64: 45717.753 | E64: 0 | F64: =IF(E64=(SUMIFS(stock_movements_coldchain[signed_qty],stock_movements_coldchain[product_id],C64,stock_movements_coldchain[warehouse_id],B64,stock_movements_coldchain[movement_date],"<" &'cycle_counts_coldchain'!D64)),"Pass","Investigate") -> Pass | G64: 3 | H64: 3 | I64: =IF((G64-E64)=H64,"Pass","Investigate") -> Pass | J64: Cycle | K64: S. Bello | L64: Near Expiry Review
A65: CC000064 | B65: WH-JOS-01 | C65: PRD00171 | D65: 45771.96 | E65: 0 | F65: =IF(E65=(SUMIFS(stock_movements_coldchain[signed_qty],stock_movements_coldchain[product_id],C65,stock_movements_coldchain[warehouse_id],B65,stock_movements_coldchain[movement_date],"<" &'cycle_counts_coldchain'!D65)),"Pass","Investigate") -> Pass | G65: 3 | H65: 3 | I65: =IF((G65-E65)=H65,"Pass","Investigate") -> Pass | J65: Cycle | K65: F. Adebayo | L65: Fefo Check
A66: CC000065 | B66: WH-KAD-01 | C66: PRD00111 | D66: 45716.059 | E66: 0 | F66: =IF(E66=(SUMIFS(stock_movements_coldchain[signed_qty],stock_movements_coldchain[product_id],C66,stock_movements_coldchain[warehouse_id],B66,stock_movements_coldchain[movement_date],"<" &'cycle_counts_coldchain'!D66)),"Pass","Investigate") -> Pass | G66: 0 | H66: 0 | I66: =IF((G66-E66)=H66,"Pass","Investigate") -> Pass | J66: Spot | K66: A. Ibrahim | L66: Fefo Check
A67: CC000066 | B67: WH-KAD-01 | C67: PRD00166 | D67: 45727.204 | E67: 0 | F67: =IF(E67=(SUMIFS(stock_movements_coldchain[signed_qty],stock_movements_coldchain[product_id],C67,stock_movements_coldchain[warehouse_id],B67,stock_movements_coldchain[movement_date],"<" &'cycle_counts_coldchain'!D67)),"Pass","Investigate") -> Pass | G67: 0 | H67: 0 | I67: =IF((G67-E67)=H67,"Pass","Investigate") -> Pass | J67: Full | K67: A. Ibrahim | L67: Fefo Check
A68: CC000067 | B68: WH-LAG-01 | C68: PRD00035 | D68: 45717.449 | E68: 0 | F68: =IF(E68=(SUMIFS(stock_movements_coldchain[signed_qty],stock_movements_coldchain[product_id],C68,stock_movements_coldchain[warehouse_id],B68,stock_movements_coldchain[movement_date],"<" &'cycle_counts_coldchain'!D68)),"Pass","Investigate") -> Pass | G68: 0 | H68: 0 | I68: =IF((G68-E68)=H68,"Pass","Investigate") -> Pass | J68: Full | K68: I. Musa | L68: Cold Room Audit
A69: CC000068 | B69: WH-LAG-01 | C69: PRD00171 | D69: 45720.526 | E69: 0 | F69: =IF(E69=(SUMIFS(stock_movements_coldchain[signed_qty],stock_movements_coldchain[product_id],C69,stock_movements_coldchain[warehouse_id],B69,stock_movements_coldchain[movement_date],"<" &'cycle_counts_coldchain'!D69)),"Pass","Investigate") -> Pass | G69: 0 | H69: 0 | I69: =IF((G69-E69)=H69,"Pass","Investigate") -> Pass | J69: Full | K69: F. Adebayo | L69: Cold Room Audit
A70: CC000069 | B70: WH-JOS-01 | C70: PRD00010 | D70: 45757.801 | E70: 0 | F70: =IF(E70=(SUMIFS(stock_movements_coldchain[signed_qty],stock_movements_coldchain[product_id],C70,stock_movements_coldchain[warehouse_id],B70,stock_movements_coldchain[movement_date],"<" &'cycle_counts_coldchain'!D70)),"Pass","Investigate") -> Pass | G70: 0 | H70: 0 | I70: =IF((G70-E70)=H70,"Pass","Investigate") -> Pass | J70: Full | K70: A. Ibrahim
A71: CC000070 | B71: WH-PHC-01 | C71: PRD00038 | D71: 45682.303 | E71: 0 | F71: =IF(E71=(SUMIFS(stock_movements_coldchain[signed_qty],stock_movements_coldchain[product_id],C71,stock_movements_coldchain[warehouse_id],B71,stock_movements_coldchain[movement_date],"<" &'cycle_counts_coldchain'!D71)),"Pass","Investigate") -> Pass | G71: 0 | H71: 0 | I71: =IF((G71-E71)=H71,"Pass","Investigate") -> Pass | J71: Full | K71: F. Adebayo | L71: Near Expiry Review
A72: CC000071 | B72: WH-PHC-01 | C72: PRD00074 | D72: 45712.977 | E72: 0 | F72: =IF(E72=(SUMIFS(stock_movements_coldchain[signed_qty],stock_movements_coldchain[product_id],C72,stock_movements_coldchain[warehouse_id],B72,stock_movements_coldchain[movement_date],"<" &'cycle_counts_coldchain'!D72)),"Pass","Investigate") -> Pass | G72: 3 | H72: 3 | I72: =IF((G72-E72)=H72,"Pass","Investigate") -> Pass | J72: Cycle | K72: A. Ibrahim | L72: Cold Room Audit
A73: CC000072 | B73: WH-BEN-01 | C73: PRD00037 | D73: 45696.236 | E73: 0 | F73: =IF(E73=(SUMIFS(stock_movements_coldchain[signed_qty],stock_movements_coldchain[product_id],C73,stock_movements_coldchain[warehouse_id],B73,stock_movements_coldchain[movement_date],"<" &'cycle_counts_coldchain'!D73)),"Pass","Investigate") -> Pass | G73: 0 | H73: 0 | I73: =IF((G73-E73)=H73,"Pass","Investigate") -> Pass | J73: Spot | K73: I. Musa | L73: Fefo Check
A74: CC000073 | B74: WH-JOS-01 | C74: PRD00037 | D74: 45726.134 | E74: 0 | F74: =IF(E74=(SUMIFS(stock_movements_coldchain[signed_qty],stock_movements_coldchain[product_id],C74,stock_movements_coldchain[warehouse_id],B74,stock_movements_coldchain[movement_date],"<" &'cycle_counts_coldchain'!D74)),"Pass","Investigate") -> Pass | G74: 0 | H74: 0 | I74: =IF((G74-E74)=H74,"Pass","Investigate") -> Pass | J74: Full | K74: I. Musa | L74: Cold Room Audit
A75: CC000074 | B75: WH-ABJ-01 | C75: PRD00112 | D75: 45721.123 | E75: 0 | F75: =IF(E75=(SUMIFS(stock_movements_coldchain[signed_qty],stock_movements_coldchain[product_id],C75,stock_movements_coldchain[warehouse_id],B75,stock_movements_coldchain[movement_date],"<" &'cycle_counts_coldchain'!D75)),"Pass","Investigate") -> Pass | G75: 2 | H75: 2 | I75: =IF((G75-E75)=H75,"Pass","Investigate") -> Pass | J75: Full | K75: I. Musa | L75: Fefo Check
A76: CC000075 | B76: WH-JOS-01 | C76: PRD00010 | D76: 45702.058 | E76: 0 | F76: =IF(E76=(SUMIFS(stock_movements_coldchain[signed_qty],stock_movements_coldchain[product_id],C76,stock_movements_coldchain[warehouse_id],B76,stock_movements_coldchain[movement_date],"<" &'cycle_counts_coldchain'!D76)),"Pass","Investigate") -> Pass | G76: 2 | H76: 2 | I76: =IF((G76-E76)=H76,"Pass","Investigate") -> Pass | J76: Spot | K76: A. Ibrahim | L76: Fefo Check
A77: CC000076 | B77: WH-ABJ-01 | C77: PRD00074 | D77: 45740.688 | E77: 0 | F77: =IF(E77=(SUMIFS(stock_movements_coldchain[signed_qty],stock_movements_coldchain[product_id],C77,stock_movements_coldchain[warehouse_id],B77,stock_movements_coldchain[movement_date],"<" &'cycle_counts_coldchain'!D77)),"Pass","Investigate") -> Pass | G77: 0 | H77: 0 | I77: =IF((G77-E77)=H77,"Pass","Investigate") -> Pass | J77: Spot | K77: A. Ibrahim | L77: Near Expiry Review
A78: CC000077 | B78: WH-PHC-01 | C78: PRD00057 | D78: 45731.135 | E78: 0 | F78: =IF(E78=(SUMIFS(stock_movements_coldchain[signed_qty],stock_movements_coldchain[product_id],C78,stock_movements_coldchain[warehouse_id],B78,stock_movements_coldchain[movement_date],"<" &'cycle_counts_coldchain'!D78)),"Pass","Investigate") -> Pass | G78: 0 | H78: 0 | I78: =IF((G78-E78)=H78,"Pass","Investigate") -> Pass | J78: Full | K78: I. Musa | L78: Cold Room Audit
A79: CC000078 | B79: WH-BEN-01 | C79: PRD00101 | D79: 45679.132 | E79: 0 | F79: =IF(E79=(SUMIFS(stock_movements_coldchain[signed_qty],stock_movements_coldchain[product_id],C79,stock_movements_coldchain[warehouse_id],B79,stock_movements_coldchain[movement_date],"<" &'cycle_counts_coldchain'!D79)),"Pass","Investigate") -> Pass | G79: 0 | H79: 0 | I79: =IF((G79-E79)=H79,"Pass","Investigate") -> Pass | J79: Spot | K79: I. Musa | L79: Cold Room Audit
A80: CC000079 | B80: WH-KAD-01 | C80: PRD00019 | D80: 45701.174 | E80: 0 | F80: =IF(E80=(SUMIFS(stock_movements_coldchain[signed_qty],stock_movements_coldchain[product_id],C80,stock_movements_coldchain[warehouse_id],B80,stock_movements_coldchain[movement_date],"<" &'cycle_counts_coldchain'!D80)),"Pass","Investigate") -> Pass | G80: 1 | H80: 1 | I80: =IF((G80-E80)=H80,"Pass","Investigate") -> Pass | J80: Spot | K80: F. Adebayo
A81: CC000080 | B81: WH-LAG-02 | C81: PRD00091 | D81: 45711.748 | E81: 0 | F81: =IF(E81=(SUMIFS(stock_movements_coldchain[signed_qty],stock_movements_coldchain[product_id],C81,stock_movements_coldchain[warehouse_id],B81,stock_movements_coldchain[movement_date],"<" &'cycle_counts_coldchain'!D81)),"Pass","Investigate") -> Pass | G81: 0 | H81: 0 | I81: =IF((G81-E81)=H81,"Pass","Investigate") -> Pass | J81: Cycle | K81: I. Musa
A82: CC000081 | B82: WH-ENU-01 | C82: PRD00156 | D82: 45731.419 | E82: 0 | F82: =IF(E82=(SUMIFS(stock_movements_coldchain[signed_qty],stock_movements_coldchain[product_id],C82,stock_movements_coldchain[warehouse_id],B82,stock_movements_coldchain[movement_date],"<" &'cycle_counts_coldchain'!D82)),"Pass","Investigate") -> Pass | G82: 0 | H82: 0 | I82: =IF((G82-E82)=H82,"Pass","Investigate") -> Pass | J82: Cycle | K82: F. Adebayo | L82: Fefo Check
A83: CC000082 | B83: WH-KAD-01 | C83: PRD00093 | D83: 45770.601 | E83: 0 | F83: =IF(E83=(SUMIFS(stock_movements_coldchain[signed_qty],stock_movements_coldchain[product_id],C83,stock_movements_coldchain[warehouse_id],B83,stock_movements_coldchain[movement_date],"<" &'cycle_counts_coldchain'!D83)),"Pass","Investigate") -> Pass | G83: 1 | H83: 1 | I83: =IF((G83-E83)=H83,"Pass","Investigate") -> Pass | J83: Full | K83: A. Ibrahim | L83: Cold Room Audit
A84: CC000083 | B84: WH-LAG-02 | C84: PRD00012 | D84: 45767.25 | E84: 0 | F84: =IF(E84=(SUMIFS(stock_movements_coldchain[signed_qty],stock_movements_coldchain[product_id],C84,stock_movements_coldchain[warehouse_id],B84,stock_movements_coldchain[movement_date],"<" &'cycle_counts_coldchain'!D84)),"Pass","Investigate") -> Pass | G84: 0 | H84: 0 | I84: =IF((G84-E84)=H84,"Pass","Investigate") -> Pass | J84: Full | K84: F. Adebayo | L84: Near Expiry Review
A85: CC000084 | B85: WH-LAG-02 | C85: PRD00113 | D85: 45679.793 | E85: 0 | F85: =IF(E85=(SUMIFS(stock_movements_coldchain[signed_qty],stock_movements_coldchain[product_id],C85,stock_movements_coldchain[warehouse_id],B85,stock_movements_coldchain[movement_date],"<" &'cycle_counts_coldchain'!D85)),"Pass","Investigate") -> Pass | G85: 0 | H85: 0 | I85: =IF((G85-E85)=H85,"Pass","Investigate") -> Pass | J85: Cycle | K85: S. Bello | L85: Near Expiry Review
A86: CC000085 | B86: WH-IBA-01 | C86: PRD00076 | D86: 45715.276 | E86: 0 | F86: =IF(E86=(SUMIFS(stock_movements_coldchain[signed_qty],stock_movements_coldchain[product_id],C86,stock_movements_coldchain[warehouse_id],B86,stock_movements_coldchain[movement_date],"<" &'cycle_counts_coldchain'!D86)),"Pass","Investigate") -> Pass | G86: 0 | H86: 0 | I86: =IF((G86-E86)=H86,"Pass","Investigate") -> Pass | J86: Spot | K86: A. Ibrahim
A87: CC000086 | B87: WH-ABJ-01 | C87: PRD00051 | D87: 45702.444 | E87: 0 | F87: =IF(E87=(SUMIFS(stock_movements_coldchain[signed_qty],stock_movements_coldchain[product_id],C87,stock_movements_coldchain[warehouse_id],B87,stock_movements_coldchain[movement_date],"<" &'cycle_counts_coldchain'!D87)),"Pass","Investigate") -> Pass | G87: 0 | H87: 0 | I87: =IF((G87-E87)=H87,"Pass","Investigate") -> Pass | J87: Spot | K87: F. Adebayo | L87: Near Expiry Review
A88: CC000087 | B88: WH-BEN-01 | C88: PRD00078 | D88: 45683.64 | E88: 0 | F88: =IF(E88=(SUMIFS(stock_movements_coldchain[signed_qty],stock_movements_coldchain[product_id],C88,stock_movements_coldchain[warehouse_id],B88,stock_movements_coldchain[movement_date],"<" &'cycle_counts_coldchain'!D88)),"Pass","Investigate") -> Pass | G88: 1 | H88: 1 | I88: =IF((G88-E88)=H88,"Pass","Investigate") -> Pass | J88: Full | K88: A. Ibrahim | L88: Fefo Check
A89: CC000088 | B89: WH-ENU-01 | C89: PRD00052 | D89: 45755.906 | E89: 0 | F89: =IF(E89=(SUMIFS(stock_movements_coldchain[signed_qty],stock_movements_coldchain[product_id],C89,stock_movements_coldchain[warehouse_id],B89,stock_movements_coldchain[movement_date],"<" &'cycle_counts_coldchain'!D89)),"Pass","Investigate") -> Pass | G89: 0 | H89: 0 | I89: =IF((G89-E89)=H89,"Pass","Investigate") -> Pass | J89: Spot | K89: A. Ibrahim | L89: Fefo Check
A90: CC000089 | B90: WH-IBA-01 | C90: PRD00002 | D90: 45728.334 | E90: 0 | F90: =IF(E90=(SUMIFS(stock_movements_coldchain[signed_qty],stock_movements_coldchain[product_id],C90,stock_movements_coldchain[warehouse_id],B90,stock_movements_coldchain[movement_date],"<" &'cycle_counts_coldchain'!D90)),"Pass","Investigate") -> Pass | G90: 2 | H90: 2 | I90: =IF((G90-E90)=H90,"Pass","Investigate") -> Pass | J90: Full | K90: I. Musa | L90: Cold Room Audit
A91: CC000090 | B91: WH-IBA-01 | C91: PRD00094 | D91: 45749.296 | E91: 0 | F91: =IF(E91=(SUMIFS(stock_movements_coldchain[signed_qty],stock_movements_coldchain[product_id],C91,stock_movements_coldchain[warehouse_id],B91,stock_movements_coldchain[movement_date],"<" &'cycle_counts_coldchain'!D91)),"Pass","Investigate") -> Pass | G91: 3 | H91: 3 | I91: =IF((G91-E91)=H91,"Pass","Investigate") -> Pass | J91: Cycle | K91: F. Adebayo | L91: Fefo Check
A92: CC000091 | B92: WH-LAG-02 | C92: PRD00091 | D92: 45736.174 | E92: 0 | F92: =IF(E92=(SUMIFS(stock_movements_coldchain[signed_qty],stock_movements_coldchain[product_id],C92,stock_movements_coldchain[warehouse_id],B92,stock_movements_coldchain[movement_date],"<" &'cycle_counts_coldchain'!D92)),"Pass","Investigate") -> Pass | G92: 0 | H92: 0 | I92: =IF((G92-E92)=H92,"Pass","Investigate") -> Pass | J92: Full | K92: I. Musa | L92: Near Expiry Review
A93: CC000092 | B93: WH-LAG-02 | C93: PRD00017 | D93: 45759.162 | E93: 0 | F93: =IF(E93=(SUMIFS(stock_movements_coldchain[signed_qty],stock_movements_coldchain[product_id],C93,stock_movements_coldchain[warehouse_id],B93,stock_movements_coldchain[movement_date],"<" &'cycle_counts_coldchain'!D93)),"Pass","Investigate") -> Pass | G93: 0 | H93: 0 | I93: =IF((G93-E93)=H93,"Pass","Investigate") -> Pass | J93: Full | K93: S. Bello | L93: Fefo Check
A94: CC000093 | B94: WH-ENU-01 | C94: PRD00110 | D94: 45760.603 | E94: 0 | F94: =IF(E94=(SUMIFS(stock_movements_coldchain[signed_qty],stock_movements_coldchain[product_id],C94,stock_movements_coldchain[warehouse_id],B94,stock_movements_coldchain[movement_date],"<" &'cycle_counts_coldchain'!D94)),"Pass","Investigate") -> Pass | G94: 1 | H94: 1 | I94: =IF((G94-E94)=H94,"Pass","Investigate") -> Pass | J94: Full | K94: S. Bello | L94: Fefo Check
A95: CC000094 | B95: WH-AWK-01 | C95: PRD00132 | D95: 45753.922 | E95: 0 | F95: =IF(E95=(SUMIFS(stock_movements_coldchain[signed_qty],stock_movements_coldchain[product_id],C95,stock_movements_coldchain[warehouse_id],B95,stock_movements_coldchain[movement_date],"<" &'cycle_counts_coldchain'!D95)),"Pass","Investigate") -> Pass | G95: 0 | H95: 0 | I95: =IF((G95-E95)=H95,"Pass","Investigate") -> Pass | J95: Spot | K95: S. Bello | L95: Fefo Check
A96: CC000095 | B96: WH-JOS-01 | C96: PRD00149 | D96: 45756.533 | E96: 0 | F96: =IF(E96=(SUMIFS(stock_movements_coldchain[signed_qty],stock_movements_coldchain[product_id],C96,stock_movements_coldchain[warehouse_id],B96,stock_movements_coldchain[movement_date],"<" &'cycle_counts_coldchain'!D96)),"Pass","Investigate") -> Pass | G96: 0 | H96: 0 | I96: =IF((G96-E96)=H96,"Pass","Investigate") -> Pass | J96: Cycle | K96: A. Ibrahim | L96: Near Expiry Review
A97: CC000096 | B97: WH-LAG-02 | C97: PRD00028 | D97: 45760.152 | E97: 0 | F97: =IF(E97=(SUMIFS(stock_movements_coldchain[signed_qty],stock_movements_coldchain[product_id],C97,stock_movements_coldchain[warehouse_id],B97,stock_movements_coldchain[movement_date],"<" &'cycle_counts_coldchain'!D97)),"Pass","Investigate") -> Pass | G97: 0 | H97: 0 | I97: =IF((G97-E97)=H97,"Pass","Investigate") -> Pass | J97: Spot | K97: I. Musa | L97: Fefo Check
A98: CC000097 | B98: WH-LAG-02 | C98: PRD00107 | D98: 45755.677 | E98: 0 | F98: =IF(E98=(SUMIFS(stock_movements_coldchain[signed_qty],stock_movements_coldchain[product_id],C98,stock_movements_coldchain[warehouse_id],B98,stock_movements_coldchain[movement_date],"<" &'cycle_counts_coldchain'!D98)),"Pass","Investigate") -> Pass | G98: 3 | H98: 3 | I98: =IF((G98-E98)=H98,"Pass","Investigate") -> Pass | J98: Full | K98: S. Bello
A99: CC000098 | B99: WH-LAG-01 | C99: PRD00084 | D99: 45738.108 | E99: 0 | F99: =IF(E99=(SUMIFS(stock_movements_coldchain[signed_qty],stock_movements_coldchain[product_id],C99,stock_movements_coldchain[warehouse_id],B99,stock_movements_coldchain[movement_date],"<" &'cycle_counts_coldchain'!D99)),"Pass","Investigate") -> Pass | G99: 0 | H99: 0 | I99: =IF((G99-E99)=H99,"Pass","Investigate") -> Pass | J99: Cycle | K99: I. Musa
A100: CC000099 | B100: WH-AWK-01 | C100: PRD00026 | D100: 45736.137 | E100: 0 | F100: =IF(E100=(SUMIFS(stock_movements_coldchain[signed_qty],stock_movements_coldchain[product_id],C100,stock_movements_coldchain[warehouse_id],B100,stock_movements_coldchain[movement_date],"<" &'cycle_counts_coldchain'!D100)),"Pass","Investigate") -> Pass | G100: 0 | H100: 0 | I100: =IF((G100-E100)=H100,"Pass","Investigate") -> Pass | J100: Cycle | K100: I. Musa | L100: Cold Room Audit
...

Sheet temperature_logs_coldchain
A1: log_id | B1: warehouse_id | C1: warehouse_name | D1: log_time | E1: setpoint_c | F1: temperature_c | G1: humidity_pct | H1: sensor_status | I1: excursion_flag
A2: TL000001 | B2: WH-LAG-01 | C2: Lagos North Cold Hub | D2: 45737.915 | E2: 3 | F2: 3.1 | G2: 64 | H2: OK | I2: N
A3: TL000002 | B3: WH-LAG-01 | C3: Lagos North Cold Hub | D3: 45746.297 | E3: 3 | F3: 2 | G3: 61 | H3: OK | I3: N
A4: TL000003 | B4: WH-LAG-01 | C4: Lagos North Cold Hub | D4: 45766.742 | E4: 3 | F4: 3.1 | G4: 83 | H4: OK | I4: N
A5: TL000004 | B5: WH-LAG-01 | C5: Lagos North Cold Hub | D5: 45765.852 | E5: 3 | F5: 3.1 | G5: 66 | H5: OK | I5: N
A6: TL000005 | B6: WH-LAG-01 | C6: Lagos North Cold Hub | D6: 45716.798 | E6: 2 | F6: 3.3 | G6: 71 | H6: WARN | I6: Y
A7: TL000006 | B7: WH-LAG-01 | C7: Lagos North Cold Hub | D7: 45663.513 | E7: 4 | F7: 3 | G7: 51 | H7: OK | I7: N
A8: TL000007 | B8: WH-LAG-01 | C8: Lagos North Cold Hub | D8: 45738.932 | E8: 3 | F8: -1.2 | G8: 55 | H8: OK | I8: Y
A9: TL000008 | B9: WH-LAG-01 | C9: Lagos North Cold Hub | D9: 45692.931 | E9: 3 | F9: 2.8 | G9: 57 | H9: OK | I9: N
A10: TL000009 | B10: WH-LAG-01 | C10: Lagos North Cold Hub | D10: 45670.934 | E10: 4 | F10: 3.9 | G10: 53 | H10: OK | I10: N
A11: TL000010 | B11: WH-LAG-01 | C11: Lagos North Cold Hub | D11: 45675.014 | E11: 2 | F11: 0.9 | G11: 70 | H11: OK | I11: N
A12: TL000011 | B12: WH-LAG-01 | C12: Lagos North Cold Hub | D12: 45703.248 | E12: 3 | F12: 8.5 | G12: 57 | H12: WARN | I12: Y
A13: TL000012 | B13: WH-LAG-01 | C13: Lagos North Cold Hub | D13: 45728.483 | E13: 4 | F13: 4.1 | G13: 62 | H13: WARN | I13: Y
... A241: TL000240 | B241: WH-AWK-01 | C241: Awka Micro Hub | D241: 45758.735 | E241: 2 | F241: 2.1 | G241: 64 | H241: OK | I241: N

Sheet Purchase_Order_tracking_sheet
A1: po_line_id | B1: product_id | C1: supplier_id | D1: expected_delivery_day | E1: ordered_qty | F1: received_qty | G1: delivery_status
A2: POL000001 | B2: PRD00161 | C2: SUP00061 | D2: 45690 | E2: 85 | F2: 84 | G2: =IF(E2-F2 <> 0, TEXT(F2/E2, "0%") & " of goods arrived", IF(E2=F2, "All goods arrived", "All goods missing")) -> 99% of goods arrived
A3: POL000002 | B3: PRD00161 | C3: SUP00061 | D3: 45690 | E3: 96 | F3: 92 | G3: =IF(E3-F3 <> 0, TEXT(F3/E3, "0%") & " of goods arrived", IF(E3=F3, "All goods arrived", "All goods missing")) -> 96% of goods arrived
A4: POL000003 | B4: PRD00161 | C4: SUP00061 | D4: 45690 | E4: 169 | F4: 144 | G4: =IF(E4-F4 <> 0, TEXT(F4/E4, "0%") & " of goods arrived", IF(E4=F4, "All goods arrived", "All goods missing")) -> 85% of goods arrived
A5: POL000004 | B5: PRD00067 | C5: SUP00101 | D5: 45677 | E5: 144 | F5: 0 | G5: =IF(E5-F5 <> 0, TEXT(F5/E5, "0%") & " of goods arrived", IF(E5=F5, "All goods arrived", "All goods missing")) -> 0% of goods arrived
A6: POL000005 | B6: PRD00033 | C6: SUP00101 | D6: 45677 | E6: 237 | F6: 195 | G6: =IF(E6-F6 <> 0, TEXT(F6/E6, "0%") & " of goods arrived", IF(E6=F6, "All goods arrived", "All goods missing")) -> 82% of goods arrived
A7: POL000006 | B7: PRD00178 | C7: SUP00089 | D7: 45668 | E7: 64 | F7: 49 | G7: =IF(E7-F7 <> 0, TEXT(F7/E7, "0%") & " of goods arrived", IF(E7=F7, "All goods arrived", "All goods missing")) -> 77% of goods arrived
A8: POL000007 | B8: PRD00011 | C8: SUP00089 | D8: 45668 | E8: 156 | F8: 121 | G8: =IF(E8-F8 <> 0, TEXT(F8/E8, "0%") & " of goods arrived", IF(E8=F8, "All goods arrived", "All goods missing")) -> 78% of goods arrived
A9: POL000008 | B9: PRD00007 | C9: SUP00004 | D9: 45686 | E9: 105 | F9: 93 | G9: =IF(E9-F9 <> 0, TEXT(F9/E9, "0%") & " of goods arrived", IF(E9=F9, "All goods arrived", "All goods missing")) -> 89% of goods arrived
A10: POL000009 | B10: PRD00058 | C10: SUP00004 | D10: 45686 | E10: 104 | F10: 85 | G10: =IF(E10-F10 <> 0, TEXT(F10/E10, "0%") & " of goods arrived", IF(E10=F10, "All goods arrived", "All goods missing")) -> 82% of goods arrived
A11: POL000010 | B11: PRD00141 | C11: SUP00004 | D11: 45686 | E11: 96 | F11: 93 | G11: =IF(E11-F11 <> 0, TEXT(F11/E11, "0%") & " of goods arrived", IF(E11=F11, "All goods arrived", "All goods missing")) -> 97% of goods arrived
A12: POL000011 | B12: PRD00170 | C12: SUP00059 | D12: 45691 | E12: 29 | F12: 0 | G12: =IF(E12-F12 <> 0, TEXT(F12/E12, "0%") & " of goods arrived", IF(E12=F12, "All goods arrived", "All goods missing")) -> 0% of goods arrived
A13: POL000012 | B13: PRD00147 | C13: SUP00059 | D13: 45691 | E13: 130 | F13: 113 | G13: =IF(E13-F13 <> 0, TEXT(F13/E13, "0%") & " of goods arrived", IF(E13=F13, "All goods arrived", "All goods missing")) -> 87% of goods arrived
... A421: POL000420 | B421: PRD00064 | C421: SUP00117 | D421: 45690 | E421: 123 | F421: 114 | G421: =IF(E421-F421 <> 0, TEXT(F421/E421, "0%") & " of goods arrived", IF(E421=F421, "All goods arrived", "All goods missing")) -> 93% of goods arrived

Sheet Warehouse_Transfer_Log
A1: reference_id | B1: Moved_quantity | C1: Received_quantity | D1: Shrinkage Check
A2: XFER-000601 | B2: 1 | C2: 1 | D2: =IF(B2=C2, "No Shrinkage Detected", "Shrinkage Detected") -> No Shrinkage Detected
A3: XFER-000603 | B3: 4 | C3: 4 | D3: =IF(B3=C3, "No Shrinkage Detected", "Shrinkage Detected") -> No Shrinkage Detected
A4: XFER-000605 | B4: 5 | C4: 5 | D4: =IF(B4=C4, "No Shrinkage Detected", "Shrinkage Detected") -> No Shrinkage Detected
A5: XFER-000607 | B5: 2 | C5: 2 | D5: =IF(B5=C5, "No Shrinkage Detected", "Shrinkage Detected") -> No Shrinkage Detected
A6: XFER-000609 | B6: 1 | C6: 1 | D6: =IF(B6=C6, "No Shrinkage Detected", "Shrinkage Detected") -> No Shrinkage Detected
A7: XFER-000611 | B7: 7 | C7: 7 | D7: =IF(B7=C7, "No Shrinkage Detected", "Shrinkage Detected") -> No Shrinkage Detected
A8: XFER-000613 | B8: 5 | C8: 5 | D8: =IF(B8=C8, "No Shrinkage Detected", "Shrinkage Detected") -> No Shrinkage Detected
A9: XFER-000615 | B9: 7 | C9: 7 | D9: =IF(B9=C9, "No Shrinkage Detected", "Shrinkage Detected") -> No Shrinkage Detected
A10: XFER-000617 | B10: 4 | C10: 4 | D10: =IF(B10=C10, "No Shrinkage Detected", "Shrinkage Detected") -> No Shrinkage Detected
A11: XFER-000619 | B11: 3 | C11: 3 | D11: =IF(B11=C11, "No Shrinkage Detected", "Shrinkage Detected") -> No Shrinkage Detected
A12: XFER-000621 | B12: 7 | C12: 7 | D12: =IF(B12=C12, "No Shrinkage Detected", "Shrinkage Detected") -> No Shrinkage Detected
A13: XFER-000623 | B13: 4 | C13: 4 | D13: =IF(B13=C13, "No Shrinkage Detected", "Shrinkage Detected") -> No Shrinkage Detected
... A16: XFER-000629 | B16: 2 | C16: 2 | D16: =IF(B16=C16, "No Shrinkage Detected", "Shrinkage Detected") -> No Shrinkage Detected

Sheet Warehouse_Writeoff_Summary
A1: warehouse_id | B1: total_qty | C1: damaged_write_off_qty | D1: temprature_write_off_qty
A2: WH-ABJ-01 | B2: 5341 | C2: 14 | D2: 0
A3: WH-IBA-01 | B3: 4517 | C3: 2 | D3: 17
A4: WH-PHC-01 | B4: 4212 | C4: 4 | D4: 4
A5: WH-KAD-01 | B5: 3790 | C5: 0 | D5: 1
A6: WH-BEN-01 | B6: 3568 | C6: 9 | D6: 0
A7: WH-ENU-01 | B7: 3563 | C7: 0 | D7: 4
A8: WH-LAG-01 | B8: 3106 | C8: 7 | D8: 4
A9: WH-AWK-01 | B9: 2906 | C9: 4 | D9: 2
A10: WH-JOS-01 | B10: 2638 | C10: 4 | D10: 0
A11: WH-LAG-02 | B11: 2557 | C11: 0 | D11: 4

Sheet Warehouse_Health_Status_Report
A1: warehouse_id | B1: Warning_count | C1: Offline_count
A2: WH-LAG-01 | B2: 3 | C2: 0
A3: WH-LAG-02 | B3: 2 | C3: 0
A4: WH-ABJ-01 | B4: 2 | C4: 0
A5: WH-PHC-01 | B5: 2 | C5: 1
A6: WH-IBA-01 | B6: 0 | C6: 1
A7: WH-ENU-01 | B7: 3 | C7: 0
A8: WH-KAD-01 | B8: 0 | C8: 0
A9: WH-JOS-01 | B9: 2 | C9: 0
A10: WH-BEN-01 | B10: 2 | C10: 1
A11: WH-AWK-01 | B11: 1 | C11: 0

Sheet Supplier_Performance_Report
A3: Supplier ID | B3: Ordered Quantity | C3: Received Quantity | D3: Supplier Fulfilment Rate
A4: SUP00001 | B4: 473 | C4: 200 | D4: 0.42283298
A5: SUP00002 | B5: 472 | C5: 113 | D5: 0.23940678
A6: SUP00004 | B6: 993 | C6: 751 | D6: 0.75629406
A7: SUP00005 | B7: 319 | C7: 276 | D7: 0.86520376
A8: SUP00008 | B8: 219 | C8: 109 | D8: 0.49771689
A9: SUP00009 | B9: 53 | C9: 45 | D9: 0.8490566
A10: SUP00011 | B10: 925 | C10: 324 | D10: 0.35027027
A11: SUP00012 | B11: 413 | C11: 342 | D11: 0.82808717
A12: SUP00013 | B12: 2237 | C12: 1619 | D12: 0.72373715
A13: SUP00014 | B13: 231 | C13: 120 | D13: 0.51948052
A14: SUP00015 | B14: 364 | C14: 185 | D14: 0.50824176
A15: SUP00019 | B15: 354 | C15: 263 | D15: 0.74293785
... A90: SUP00120 | B90: 178 | C90: 0 | D90: 0

Sheet Column Lineage
A1: Column Name | B1: Data Type | C1: Source Sheet | D1: Transformation Applied | E1: Example
A2: line_total_actual | B2: Intergers | C2: purchase_order_lines_coldchain | D2: Rule based Classification | E2: 980.44
A3: line_total_Check | B3: Text | C3: purchase_order_lines_coldchain | D3: Rule based Classification | E3: Investigate
A4: missing_reference_id_check | B4: Intergers | C4: stock_movements_coldchain | D4: Rule based Classification | E4: PO000031
A5: reference_id_actual | B5: Intergers | C5: stock_movements_coldchain | D5: Rule based Classification | E5: PO000031
A6: system_qty_Check | B6: Text | C6: cycle_counts_coldchain | D6: Rule based Classification | E6: Pass
A7: variance_check | B7: Text | C7: cycle_counts_coldchain | D7: Rule based Classification | E7: Pass
A8: delivery_status | B8: Intergers | C8: Purchase_Order_tracking_sheet | D8: Rule based Classification | E8: All goods arrived
A9: Shrinkage Check | B9: Text | C9: Warehouse_Transfer_Log | D9: Rule based Classification | E9: No Shrinkage Detected

Sheet Validation Tests
A1: Check Name | B1: What is being Checked | C1: Formula Used | D1: Expected Result | E1: Actual Result | F1: Status
A2: line_total_actual | B2: The actual Total/Calculation of a Purchase Order Line | C2: ROUND((H2*I2)-(J2/100)*(H2*I2),2) | D2: 310.78 | E2: 310.78 | F2: Passed
A3: line_total_Check | B3: Where Previous Claculation(line_total) was Wrong | C3: IF(K2=L2,"Pass",IF(K2=L2-0.01,"Pass","Investigate")) | D3: Pass | E3: Pass | F3: Passed
A4: missing_reference_id_check | B4: Missing Refrence ID | C4: IF(AND(G2="",C2="Receipt"), XLOOKUP(1, (purchase_order_lines_coldchain!A2:A1000 = F2) * (purchase_order_lines_coldchain!G2:G1000 = E2) * (purchase_order_lines_coldchain!D2:D1000 = D2), purchase_order_lines_coldchain!B$2:B$1000, XLOOKUP(F2,purchase_order_lines_coldchain!A$2:A1000, purchase_order_lines_coldchain!B$2:B1000)), "") | D4: ="" | E4: ="" | F4: Passed
A5: reference_id_actual | B5: Ensuring Missing Refrence ID and Existing Refrence Id are In the same column | D5: ="" | E5: ="" | F5: Passed
A6: system_qty_Check | B6: Ensuring what is Recorded is what is in the actual system | C6: IF(E2=(SUMIFS(stock_movements_coldchain[signed_qty],stock_movements_coldchain[product_id],C2,stock_movements_coldchain[warehouse_id],B2,stock_movements_coldchain[movement_date],"<" &'cycle_counts_coldchain'!D2)),"Pass","Investigate") | D6: Pass | E6: Pass | F6: Passed
A7: variance_check | B7: Ensuring what is Recorded is the actual variance | C7: IF((G2-E2)=H2,"Pass","Investigate") | D7: Pass | E7: Pass | F7: Passed
A8: delivery_status | B8: How Many Percent Of Goods Ordered actually Arrived | C8: IF(E2-F2 <> 0, TEXT(F2/E2, "0%") & " of goods arrived", IF(E2=F2, "All goods arrived", "All goods missing")) | D8: 99% of goods arrived | E8: 99% of goods arrived | F8: Passed
A9: Shrinkage Check | B9: Did Shrinkage Occur when Moving Products between Warehouses | C9: IF(B2=C2, "No Shrinkage Detected", "Shrinkage Detected") | D9: No Shrinkage Detected | E9: No Shrinkage Detected | F9: Passed

Sheet Sheet Lineage
A1: Dataset/Sheet | B1: Type | C1: Source | D1: Transformation/Process | E1: Output
A2: Cold-Chain Inventory & Shrinkage | B2: Source Data | C2: Raw Cold-Chain Inventory & Shrinkage Sheet | D2: Removed Duplicate, Joined tables, Calculations | E2: Cold-Chain Inventory & Shrinkage
A3: Purchase_Order_tracking_sheet | B3: SQL table | C3: Cold-Chain Inventory & Shrinkage | D3: Ran Query to track Specific Products from Suppliers to Company X | E3: Purchase_Order_tracking_sheet
A4: Warehouse_Transfer_Log | B4: SQL table | C4: Cold-Chain Inventory & Shrinkage | D4: Ran Query to track Specific Products Movemnts from One warehouse to another | E4: Warehouse_Transfer_Log
A5: Warehouse_Writeoff_Summary | B5: SQL table | C5: Cold-Chain Inventory & Shrinkage | D5: Ran Query to track Quantity of Products that were Written off as well as Reason for Writeoff | E5: Warehouse_Writeoff_Summary
A6: Warehouse_Health_Status_Report | B6: SQL table | C6: Cold-Chain Inventory & Shrinkage | D6: Ran Query to track The frequency of Reported Health Issue for each Warehouse | E6: Warehouse_Health_Status_Report
A7: Supplier_Performance_Report | B7: Pivot table | C7: Purchase_Order_tracking_sheet | D7: Generated a Pivot table with Specific Columns to track Suppliers Fulfilment Better | E7: Supplier_Performance_Report

Sheet Before and After Snapshot
A1: Metrics | B1: Befoe Cleaning | C1: After Cleaning | D1: What Changed
A2: reference_id | B2: 8 Missing ID | C2: 4 Missing ID Recovered | D2: Created New column to Investigated and Recover Missing ID
A3: Number of Sheets | B3: 7 Visible Sheets | C3: 12 Visible Sheets and 4 Hidden Sheets | D3: Deeper Analysis
